[{"Title":"18_rankkurin_asunto‎ (1892–1912)","Artist":"","Date":"1892","Medium":"","CreditLine":"Helsinki City Archives — CC BY 4.0","URL":"https://finna.fi/Record/hka.139878174949000_143022726682700","ImageURL":"https://api.finna.fi/Cover/Show?source=Solr&id=hka.139878174949000_143022726682700&index=0&size=large","ObjectID":165},{"Title":"Mellunkylän kansakoulu_00023","Artist":"","Date":"","Medium":"","CreditLine":"Helsinki City Archives — CC BY 4.0","URL":"https://finna.fi/Record/hka.139878174949000_147912885143300","ImageURL":"https://api.finna.fi/Cover/Show?source=Solr&id=hka.139878174949000_147912885143300&index=0&size=large","ObjectID":1533},{"Title":"Ahmatie_4‎ (1952)","Artist":"","Date":"1952","Medium":"","CreditLine":"Helsinki City Archives — CC BY 4.0","URL":"https://finna.fi/Record/hka.139880122092100_143022729175700","ImageURL":"https://api.finna.fi/Cover/Show?source=Solr&id=hka.139880122092100_143022729175700&index=0&size=large","ObjectID":2901},{"Title":"Nikolainkatu (=  Snellmaninkatu ) 16, 18","Artist":"Brander, Signe","Date":"1908","Medium":"","CreditLine":"Helsinki City Museum — PDM","URL":"https://finna.fi/Record/hkm.05307A45-68A0-42FF-9271-EF613BC63673","ImageURL":"https://api.finna.fi/Cover/Show?source=Solr&id=hkm.05307A45-68A0-42FF-9271-EF613BC63673&index=0&size=large","ObjectID":4269},{"Title":"Malmi, Ylä-Malmi","Artist":"Rista, Simo","Date":"1970","Medium":"","CreditLine":"Helsinki City Museum — PDM","URL":"https://finna.fi/Record/hkm.0F333571-824D-4662-B0D1-1DA644EBA475","ImageURL":"https://api.finna.fi/Cover/Show?source=Solr&id=hkm.0F333571-824D-4662-B0D1-1DA644EBA475&index=0&size=large","ObjectID":5637},{"Title":"Piispat ja paavi; piirustus","Artist":"Mannerheim, August Erik","Date":"1840","Medium":"","CreditLine":"Helsinki City Museum — PDM","URL":"https://finna.fi/Record/hkm.18F191AA-A8D4-49EC-B82A-7131CA489A04","ImageURL":"https://api.finna.fi/Cover/Show?source=Solr&id=hkm.18F191AA-A8D4-49EC-B82A-7131CA489A04&index=0&size=large","ObjectID":7005},{"Title":"Paciuksenkadun laitaa Humallahdenpuiston suuntaan","Artist":"Rista, Eeva","Date":"1970","Medium":"","CreditLine":"Helsinki City Museum — PDM","URL":"https://finna.fi/Record/hkm.227C864D-9198-4479-9407-EDADC2975808","ImageURL":"https://api.finna.fi/Cover/Show?source=Solr&id=hkm.227C864D-9198-4479-9407-EDADC2975808&index=0&size=large","ObjectID":8373},{"Title":"Jäälauttoja ja roskia keväällä Siltavuorensalmessa","Artist":"Rista, Simo","Date":"1970","Medium":"","CreditLine":"Helsinki City Museum — PDM","URL":"https://finna.fi/Record/hkm.2BF60DA2-9E3F-46D3-A15F-B8C046FE208E","ImageURL":"https://api.finna.fi/Cover/Show?source=Solr&id=hkm.2BF60DA2-9E3F-46D3-A15F-B8C046FE208E&index=0&size=large","ObjectID":9741},{"Title":"Nihti","Artist":"","Date":"1939","Medium":"","CreditLine":"Helsinki City Museum — PDM","URL":"https://finna.fi/Record/hkm.3531269D-BEC2-444D-BE39-23562988D35E","ImageURL":"https://api.finna.fi/Cover/Show?source=Solr&id=hkm.3531269D-BEC2-444D-BE39-23562988D35E&index=0&size=large","ObjectID":11109},{"Title":"Tullisaari","Artist":"Rista, Simo","Date":"1970","Medium":"","CreditLine":"Helsinki City Museum — PDM","URL":"https://finna.fi/Record/hkm.3EB9FDE7-13E4-4A04-8BB5-3BE61988D6EC","ImageURL":"https://api.finna.fi/Cover/Show?source=Solr&id=hkm.3EB9FDE7-13E4-4A04-8BB5-3BE61988D6EC&index=0&size=large","ObjectID":12477},{"Title":"Velodrom, Helsingin pyöräilystadion, Suomen Työväen Urheiluliiton (TUL) tilaisuus, naisten voimisteluesitys","Artist":"Kannisto, Väinö Aleksi","Date":"1948","Medium":"","CreditLine":"Helsinki City Museum — PDM","URL":"https://finna.fi/Record/hkm.47FF1C5A-825F-4945-A108-B2641FADF449","ImageURL":"https://api.finna.fi/Cover/Show?source=Solr&id=hkm.47FF1C5A-825F-4945-A108-B2641FADF449&index=0&size=large","ObjectID":13845},{"Title":"Musiikkikauppa Frog-Music, Albertinkatu 12","Artist":"Roos, Carl-Gustav","Date":"1975","Medium":"","CreditLine":"Helsinki City Museum — PDM","URL":"https://finna.fi/Record/hkm.51761259-BF69-4727-9534-8D94810755A9","ImageURL":"https://api.finna.fi/Cover/Show?source=Solr&id=hkm.51761259-BF69-4727-9534-8D94810755A9&index=0&size=large","ObjectID":15213},{"Title":"Kauppatori","Artist":"Kajantie, Arvo","Date":"1958","Medium":"","CreditLine":"Helsinki City Museum — PDM","URL":"https://finna.fi/Record/hkm.5A80FF83-4A8A-4F43-A9A1-96980E4F84D0","ImageURL":"https://api.finna.fi/Cover/Show?source=Solr&id=hkm.5A80FF83-4A8A-4F43-A9A1-96980E4F84D0&index=0&size=large","ObjectID":16581},{"Title":"Tuntematon mies, mahdollisesti keraamikko Friedl Holzer-Kjellbergin työhuoneella","Artist":"Holzer, Maria","Date":"1925","Medium":"","CreditLine":"Helsinki City Museum — PDM","URL":"https://finna.fi/Record/hkm.641A6201-B455-46D5-B99E-DDF15610CB9A","ImageURL":"https://api.finna.fi/Cover/Show?source=Solr&id=hkm.641A6201-B455-46D5-B99E-DDF15610CB9A&index=0&size=large","ObjectID":17949},{"Title":"Kapteeninkatu 12-18","Artist":"Rista, Simo","Date":"1974","Medium":"","CreditLine":"Helsinki City Museum — PDM","URL":"https://finna.fi/Record/hkm.6D69DBE9-64B6-4824-969D-5A414735980C","ImageURL":"https://api.finna.fi/Cover/Show?source=Solr&id=hkm.6D69DBE9-64B6-4824-969D-5A414735980C&index=0&size=large","ObjectID":19317},{"Title":"Panoraama Nikolainkirkon tornista, kuva 15","Artist":"Hoffers, Carl Eugen","Date":"1866","Medium":"","CreditLine":"Helsinki City Museum — PDM","URL":"https://finna.fi/Record/hkm.76F6A992-1E56-4C5F-970F-973D5C030E1A","ImageURL":"https://api.finna.fi/Cover/Show?source=Solr&id=hkm.76F6A992-1E56-4C5F-970F-973D5C030E1A&index=0&size=large","ObjectID":20685},{"Title":"Siltasaarenkatu","Artist":"Rista, Eeva","Date":"1970","Medium":"","CreditLine":"Helsinki City Museum — PDM","URL":"https://finna.fi/Record/hkm.8092FFD4-C35D-4BE9-AFD0-BBD7B4181606","ImageURL":"https://api.finna.fi/Cover/Show?source=Solr&id=hkm.8092FFD4-C35D-4BE9-AFD0-BBD7B4181606&index=0&size=large","ObjectID":22053},{"Title":"Eläintarhantie","Artist":"Rista, Simo","Date":"1970","Medium":"","CreditLine":"Helsinki City Museum — PDM","URL":"https://finna.fi/Record/hkm.8A24C6C6-3577-4ACE-8653-106B2D3797B8","ImageURL":"https://api.finna.fi/Cover/Show?source=Solr&id=hkm.8A24C6C6-3577-4ACE-8653-106B2D3797B8&index=0&size=large","ObjectID":23421},{"Title":"Kaksi nuorta naista","Artist":"Kannisto, Väinö Aleksi","Date":"1940","Medium":"","CreditLine":"Helsinki City Museum — PDM","URL":"https://finna.fi/Record/hkm.9305D129-7F99-4B39-9E2C-4D9938F10456","ImageURL":"https://api.finna.fi/Cover/Show?source=Solr&id=hkm.9305D129-7F99-4B39-9E2C-4D9938F10456&index=0&size=large","ObjectID":24789},{"Title":"Viistoilmakuva pienlentokoneesta Töölön pallokentän suunnalta kaakkoon Kallion suuntaan","Artist":"Rista, Simo","Date":"1970","Medium":"","CreditLine":"Helsinki City Museum — PDM","URL":"https://finna.fi/Record/hkm.9C139E49-1F9F-4F04-9CB3-ECD332835A44","ImageURL":"https://api.finna.fi/Cover/Show?source=Solr&id=hkm.9C139E49-1F9F-4F04-9CB3-ECD332835A44&index=0&size=large","ObjectID":26157},{"Title":"Karhupuisto","Artist":"Rista, Simo","Date":"1970","Medium":"","CreditLine":"Helsinki City Museum — PDM","URL":"https://finna.fi/Record/hkm.A513C94E-7962-4A44-A367-B08FB97ADF9D","ImageURL":"https://api.finna.fi/Cover/Show?source=Solr&id=hkm.A513C94E-7962-4A44-A367-B08FB97ADF9D&index=0&size=large","ObjectID":27525},{"Title":"Eläintarhan ajot","Artist":"Kannisto, Väinö Aleksi","Date":"1946","Medium":"","CreditLine":"Helsinki City Museum — PDM","URL":"https://finna.fi/Record/hkm.AEB69EF5-C98D-474A-95E0-91AB0876E582","ImageURL":"https://api.finna.fi/Cover/Show?source=Solr&id=hkm.AEB69EF5-C98D-474A-95E0-91AB0876E582&index=0&size=large","ObjectID":28893},{"Title":"Tie ravintola Alppilaan","Artist":"Nyblin, Daniel","Date":"1890","Medium":"","CreditLine":"Helsinki City Museum — PDM","URL":"https://finna.fi/Record/hkm.B9140E64-0435-4902-A2D0-A229C756EC49","ImageURL":"https://api.finna.fi/Cover/Show?source=Solr&id=hkm.B9140E64-0435-4902-A2D0-A229C756EC49&index=0&size=large","ObjectID":30261},{"Title":"Raitiotien kiskojen muutostöitä Arkadiankadulla","Artist":"","Date":"1960","Medium":"","CreditLine":"Helsinki City Museum — PDM","URL":"https://finna.fi/Record/hkm.C321BA87-DC96-4DA6-B849-F88819195901","ImageURL":"https://api.finna.fi/Cover/Show?source=Solr&id=hkm.C321BA87-DC96-4DA6-B849-F88819195901&index=0&size=large","ObjectID":31629},{"Title":"Airamin kuljetuksissaan käyttämä Citroen H-mallin Camionette -pakettiauto","Artist":"","Date":"1950","Medium":"","CreditLine":"Helsinki City Museum — PDM","URL":"https://finna.fi/Record/hkm.CD4574A4-B63B-48A9-B440-AD1E4E6C5DC1","ImageURL":"https://api.finna.fi/Cover/Show?source=Solr&id=hkm.CD4574A4-B63B-48A9-B440-AD1E4E6C5DC1&index=0&size=large","ObjectID":32997},{"Title":"Eerikinkatu 11","Artist":"Rista, Simo","Date":"1970","Medium":"","CreditLine":"Helsinki City Museum — PDM","URL":"https://finna.fi/Record/hkm.D7820912-9619-4170-AA2D-6EB5E157137B","ImageURL":"https://api.finna.fi/Cover/Show?source=Solr&id=hkm.D7820912-9619-4170-AA2D-6EB5E157137B&index=0&size=large","ObjectID":34365},{"Title":"Sörnäisten sataman vanha satamakonttori (rakennettu mahd","Artist":"Pietinen, A.","Date":"1966","Medium":"","CreditLine":"Helsinki City Museum — PDM","URL":"https://finna.fi/Record/hkm.E19DA90D-5CE6-47A9-9489-AC42550D5DB9","ImageURL":"https://api.finna.fi/Cover/Show?source=Solr&id=hkm.E19DA90D-5CE6-47A9-9489-AC42550D5DB9&index=0&size=large","ObjectID":35733},{"Title":"Oy Wilh","Artist":"Pietinen:  :","Date":"1969","Medium":"","CreditLine":"Helsinki City Museum — PDM","URL":"https://finna.fi/Record/hkm.EBC1C862-D70A-414D-A710-FF9510479D5E","ImageURL":"https://api.finna.fi/Cover/Show?source=Solr&id=hkm.EBC1C862-D70A-414D-A710-FF9510479D5E&index=0&size=large","ObjectID":37101},{"Title":"kalustepiirustus, Mariankatu 9; Apotekar E. Idman Special  av skåp i badrum","Artist":"Frölander-Ulf, David; Frölander-Ulf, David","Date":"1918","Medium":"","CreditLine":"Helsinki City Museum — PDM","URL":"https://finna.fi/Record/hkm.F5625319-607A-4AF3-8E69-641D39D16A0D","ImageURL":"https://api.finna.fi/Cover/Show?source=Solr&id=hkm.F5625319-607A-4AF3-8E69-641D39D16A0D&index=0&size=large","ObjectID":38469},{"Title":"Laivoja ja veneitä Suvilahdella","Artist":"Heinonen, Eino","Date":"1950","Medium":"","CreditLine":"Helsinki City Museum — PDM","URL":"https://finna.fi/Record/hkm.FF57E69E-6AD7-46CB-8204-552CF9B7809E","ImageURL":"https://api.finna.fi/Cover/Show?source=Solr&id=hkm.FF57E69E-6AD7-46CB-8204-552CF9B7809E&index=0&size=large","ObjectID":39837},{"Title":"Mikkelin linja-autoasema","Artist":"Teuvo Karjalainen","Date":"1973","Medium":"","CreditLine":"Mikkeli City Museums — PDM","URL":"https://finna.fi/Record/mkm.166867577465800","ImageURL":"https://api.finna.fi/Cover/Show?source=Solr&id=mkm.166867577465800&index=0&size=large","ObjectID":41205},{"Title":"Pommituksesta syttynyt tulipalo Seurahuoneella, Mannerheimintie 14.","Artist":"","Date":"1940","Medium":"","CreditLine":"Mikkeli City Museums — PDM","URL":"https://finna.fi/Record/mkm.166867597238600","ImageURL":"https://api.finna.fi/Cover/Show?source=Solr&id=mkm.166867597238600&index=0&size=large","ObjectID":42573},{"Title":"Pyhätunturin Kuorinkikuru pohjoisluoteeseen","Artist":"Fabricius, Åke","Date":"1918","Medium":"","CreditLine":"Finnish Heritage Agency — PDM","URL":"https://finna.fi/Record/museovirasto.0defe840-469f-4fe3-9561-8cd3aeb9adfc","ImageURL":"https://api.finna.fi/Cover/Show?source=Solr&id=museovirasto.0defe840-469f-4fe3-9561-8cd3aeb9adfc&index=0&size=large","ObjectID":43941},{"Title":"rouva Berendt","Artist":"Nyblin, Daniel","Date":"1878","Medium":"","CreditLine":"Finnish Heritage Agency — PDM","URL":"https://finna.fi/Record/museovirasto.7A7A248557273D7863E7FD7852745C03","ImageURL":"https://api.finna.fi/Cover/Show?source=Solr&id=museovirasto.7A7A248557273D7863E7FD7852745C03&index=0&size=large","ObjectID":45309},{"Title":"Lapuanjoen ylittävä Härmän silta","Artist":"","Date":"1912","Medium":"","CreditLine":"Finnish Heritage Agency — PDM","URL":"https://finna.fi/Record/museovirasto.e024abb2-266e-470c-b3f0-ba1143d14772","ImageURL":"https://api.finna.fi/Cover/Show?source=Solr&id=museovirasto.e024abb2-266e-470c-b3f0-ba1143d14772&index=0&size=large","ObjectID":46677},{"Title":"Jannu Suklaata -tuotepakkauksia","Artist":"Turun Kivipaino Oy - Åbo Stentryckeri Ab","Date":"1958","Medium":"","CreditLine":"Turun kaupunginmuseo — CC BY 4.0","URL":"https://finna.fi/Record/tmk.160988099181000","ImageURL":"https://api.finna.fi/Cover/Show?source=Solr&id=tmk.160988099181000&index=0&size=large","ObjectID":48045},{"Title":"Olympos Täytesuklaa -etikettejä","Artist":"Turun Kivipaino Oy - Åbo Stentryckeri Ab","Date":"1952","Medium":"","CreditLine":"Turun kaupunginmuseo — CC BY 4.0","URL":"https://finna.fi/Record/tmk.160988334622500","ImageURL":"https://api.finna.fi/Cover/Show?source=Solr&id=tmk.160988334622500&index=0&size=large","ObjectID":49413},{"Title":"Jalostaja C-Vitaminoitua Mustaviinimarjamehua -etikettejä","Artist":"Turun Kivipaino Oy - Åbo Stentryckeri Ab","Date":"1956","Medium":"","CreditLine":"Turun kaupunginmuseo — CC BY 4.0","URL":"https://finna.fi/Record/tmk.160988564695100","ImageURL":"https://api.finna.fi/Cover/Show?source=Solr&id=tmk.160988564695100&index=0&size=large","ObjectID":50781},{"Title":"Osakeyhtiö Machinery Aktiebolage 10000mk Serie B. -osakekirjoja; Osakeyhtiö Machinery Aktiebolage 1000mk Serie A. -osakekirjoja; Osakeyhtiö Machinery Aktiebolage 1946-1951 -osinkokuponkeja; Osakeyhtiö Machinery Aktiebolage 1946-1951 -talonkeja","Artist":"Turun Kivipaino Oy - Åbo Stentryckeri Ab","Date":"1945","Medium":"","CreditLine":"Turun kaupunginmuseo — CC BY 4.0","URL":"https://finna.fi/Record/tmk.160988780133400","ImageURL":"https://api.finna.fi/Cover/Show?source=Solr&id=tmk.160988780133400&index=0&size=large","ObjectID":52149},{"Title":"tapettinäyte","Artist":"","Date":"","Medium":"","CreditLine":"Turun kaupunginmuseo — CC BY 4.0","URL":"https://finna.fi/Record/tmk.160989050250800","ImageURL":"https://api.finna.fi/Cover/Show?source=Solr&id=tmk.160989050250800&index=0&size=large","ObjectID":53517},{"Title":"tapetti; tapettinäyte","Artist":"","Date":"","Medium":"","CreditLine":"Turun kaupunginmuseo — CC BY 4.0","URL":"https://finna.fi/Record/tmk.160989364441900","ImageURL":"https://api.finna.fi/Cover/Show?source=Solr&id=tmk.160989364441900&index=0&size=large","ObjectID":54885},{"Title":"tuotekotelo","Artist":"Turun Kivipaino Oy - Åbo Stentryckeri Ab","Date":"1950","Medium":"","CreditLine":"Turun kaupunginmuseo — CC BY 4.0","URL":"https://finna.fi/Record/tmk.160989596629300","ImageURL":"https://api.finna.fi/Cover/Show?source=Solr&id=tmk.160989596629300&index=0&size=large","ObjectID":56253},{"Title":"mainostaulu","Artist":"Turun Kivipaino Oy - Åbo Stentryckeri Ab","Date":"1938","Medium":"","CreditLine":"Turun kaupunginmuseo — CC BY 4.0","URL":"https://finna.fi/Record/tmk.160989879037300","ImageURL":"https://api.finna.fi/Cover/Show?source=Solr&id=tmk.160989879037300&index=0&size=large","ObjectID":57621},{"Title":"tapetti; tapettinäyte","Artist":"","Date":"","Medium":"","CreditLine":"Turun kaupunginmuseo — CC BY 4.0","URL":"https://finna.fi/Record/tmk.160990164539300","ImageURL":"https://api.finna.fi/Cover/Show?source=Solr&id=tmk.160990164539300&index=0&size=large","ObjectID":58989},{"Title":"muototiili; tiili","Artist":"","Date":"","Medium":"","CreditLine":"Turun kaupunginmuseo — CC BY 4.0","URL":"https://finna.fi/Record/tmk.160990374483200","ImageURL":"https://api.finna.fi/Cover/Show?source=Solr&id=tmk.160990374483200&index=0&size=large","ObjectID":60357},{"Title":"Leikkikalu; Talousesine","Artist":"","Date":"","Medium":"","CreditLine":"Turun kaupunginmuseo — CC BY 4.0","URL":"https://finna.fi/Record/tmk.160990722613900","ImageURL":"https://api.finna.fi/Cover/Show?source=Solr&id=tmk.160990722613900&index=0&size=large","ObjectID":61725},{"Title":"kukkaro; käsilaukku; pussukka","Artist":"","Date":"1800","Medium":"","CreditLine":"The Uusikaupunki museum — PDM","URL":"https://finna.fi/Record/tmk.160991280339300","ImageURL":"https://api.finna.fi/Cover/Show?source=Solr&id=tmk.160991280339300&index=0&size=large","ObjectID":63093},{"Title":"J. A. Zachariassen & Co. varustamolippu; lippu; shipowner ́s flag","Artist":"","Date":"1902","Medium":"","CreditLine":"Forum Marinum — PDM","URL":"https://finna.fi/Record/tmk.160992007655700","ImageURL":"https://api.finna.fi/Cover/Show?source=Solr&id=tmk.160992007655700&index=0&size=large","ObjectID":64461},{"Title":"kellonperät","Artist":"","Date":"","Medium":"","CreditLine":"Turun kaupunginmuseo — CC BY 4.0","URL":"https://finna.fi/Record/tmk.160993083098000","ImageURL":"https://api.finna.fi/Cover/Show?source=Solr&id=tmk.160993083098000&index=0&size=large","ObjectID":65829},{"Title":"suomalaisen univormun nappi","Artist":"","Date":"","Medium":"","CreditLine":"Turun kaupunginmuseo — CC BY 4.0","URL":"https://finna.fi/Record/tmk.160994678135200","ImageURL":"https://api.finna.fi/Cover/Show?source=Solr&id=tmk.160994678135200&index=0&size=large","ObjectID":67197},{"Title":"veitsi","Artist":"Bror Thure Thureson; Oy Fiskars Ab","Date":"1863","Medium":"","CreditLine":"Turun kaupunginmuseo — CC BY 4.0","URL":"https://finna.fi/Record/tmk.160995901045700","ImageURL":"https://api.finna.fi/Cover/Show?source=Solr&id=tmk.160995901045700&index=0&size=large","ObjectID":68565},{"Title":"kermakko","Artist":"","Date":"","Medium":"","CreditLine":"Turun kaupunginmuseo — CC BY 4.0","URL":"https://finna.fi/Record/tmk.160997086546700","ImageURL":"https://api.finna.fi/Cover/Show?source=Solr&id=tmk.160997086546700&index=0&size=large","ObjectID":69933},{"Title":"juna, rautatie, Kalarannan seisake, kaupunkikuva; kaupunkikuva","Artist":"","Date":"1925","Medium":"","CreditLine":"The Uusikaupunki museum — PDM","URL":"https://finna.fi/Record/tmk.160997670873600","ImageURL":"https://api.finna.fi/Cover/Show?source=Solr&id=tmk.160997670873600&index=0&size=large","ObjectID":71301},{"Title":"rintakuva miehestä; henkilökuva","Artist":"","Date":"1925","Medium":"","CreditLine":"The Uusikaupunki museum — PDM","URL":"https://finna.fi/Record/tmk.160998196034200","ImageURL":"https://api.finna.fi/Cover/Show?source=Solr&id=tmk.160998196034200&index=0&size=large","ObjectID":72669},{"Title":"juomalasi; viinilasi / valkoviinilasi","Artist":"","Date":"","Medium":"","CreditLine":"Turun kaupunginmuseo — CC BY 4.0","URL":"https://finna.fi/Record/tmk.160998654351100","ImageURL":"https://api.finna.fi/Cover/Show?source=Solr&id=tmk.160998654351100&index=0&size=large","ObjectID":74037},{"Title":"kahvitus, kahvinjuonti, vanhainkoti, hoitaja kaataa kahvia.; sisäkuva","Artist":"Valokuvaamo Varjus","Date":"1968","Medium":"","CreditLine":"The Uusikaupunki museum — PDM","URL":"https://finna.fi/Record/tmk.160999093433700","ImageURL":"https://api.finna.fi/Cover/Show?source=Solr&id=tmk.160999093433700&index=0&size=large","ObjectID":75405},{"Title":"Kivitalo, Uudenkaupungin vanha raatihuone, kaupungintalo ja poliisiasema; kaupunkikuva","Artist":"","Date":"1950","Medium":"","CreditLine":"The Uusikaupunki museum — PDM","URL":"https://finna.fi/Record/tmk.160999539824600","ImageURL":"https://api.finna.fi/Cover/Show?source=Solr&id=tmk.160999539824600&index=0&size=large","ObjectID":76773},{"Title":"joulukoriste; karamelli; joulukuusen koriste","Artist":"","Date":"1930","Medium":"","CreditLine":"Turun kaupunginmuseo — CC BY 4.0","URL":"https://finna.fi/Record/tmk.160999926543700","ImageURL":"https://api.finna.fi/Cover/Show?source=Solr&id=tmk.160999926543700&index=0&size=large","ObjectID":78141},{"Title":"Tuoli","Artist":"","Date":"","Medium":"","CreditLine":"Turun kaupunginmuseo — CC BY 4.0","URL":"https://finna.fi/Record/tmk.161001087455400","ImageURL":"https://api.finna.fi/Cover/Show?source=Solr&id=tmk.161001087455400&index=0&size=large","ObjectID":79509},{"Title":"kypärä; vespakypärä","Artist":"","Date":"","Medium":"","CreditLine":"Turun kaupunginmuseo — CC BY 4.0","URL":"https://finna.fi/Record/tmk.161002524220400","ImageURL":"https://api.finna.fi/Cover/Show?source=Solr&id=tmk.161002524220400&index=0&size=large","ObjectID":80877},{"Title":"jalkineet; kengät; tyttöjen hihnakengät","Artist":"","Date":"1970","Medium":"","CreditLine":"Turun kaupunginmuseo — CC BY 4.0","URL":"https://finna.fi/Record/tmk.161004341384700","ImageURL":"https://api.finna.fi/Cover/Show?source=Solr&id=tmk.161004341384700&index=0&size=large","ObjectID":82245},{"Title":"Mortteli; huhmare","Artist":"","Date":"1920","Medium":"","CreditLine":"Turun kaupunginmuseo — CC BY 4.0","URL":"https://finna.fi/Record/tmk.161005707891500","ImageURL":"https://api.finna.fi/Cover/Show?source=Solr&id=tmk.161005707891500&index=0&size=large","ObjectID":83613},{"Title":"miesten puku / frakki (takki)","Artist":"L. Eskola","Date":"1920","Medium":"","CreditLine":"Turun kaupunginmuseo — CC BY 4.0","URL":"https://finna.fi/Record/tmk.161006833640700","ImageURL":"https://api.finna.fi/Cover/Show?source=Solr&id=tmk.161006833640700&index=0&size=large","ObjectID":84981},{"Title":"Hullunkuriset perheet; De löjliga Strix-familjerna; Pelikortit","Artist":"","Date":"1925","Medium":"","CreditLine":"Turun kaupunginmuseo — CC BY 4.0","URL":"https://finna.fi/Record/tmk.161007793955700","ImageURL":"https://api.finna.fi/Cover/Show?source=Solr&id=tmk.161007793955700&index=0&size=large","ObjectID":86349},{"Title":"koristemalli ornamenttimalli; malli","Artist":"","Date":"","Medium":"","CreditLine":"Turun kaupunginmuseo — CC BY 4.0","URL":"https://finna.fi/Record/tmk.161009025627500","ImageURL":"https://api.finna.fi/Cover/Show?source=Solr&id=tmk.161009025627500&index=0&size=large","ObjectID":87717},{"Title":"peilinkehys; valumalli","Artist":"Olavi Vauras","Date":"","Medium":"","CreditLine":"Turun kaupunginmuseo — CC BY 4.0","URL":"https://finna.fi/Record/tmk.161010091503500","ImageURL":"https://api.finna.fi/Cover/Show?source=Solr&id=tmk.161010091503500&index=0&size=large","ObjectID":89085},{"Title":"Postitalo. Posti. Asiakaspalvelutila.","Artist":"Turun Sanomat","Date":"1932","Medium":"","CreditLine":"Turun kaupunginmuseo — PDM","URL":"https://finna.fi/Record/tmk.161011851879900","ImageURL":"https://api.finna.fi/Cover/Show?source=Solr&id=tmk.161011851879900&index=0&size=large","ObjectID":90453},{"Title":"Naisvoimistelijoiden voimistelunäytös Urheilupuiston kentällä.","Artist":"Turun Sanomat","Date":"1928","Medium":"","CreditLine":"Turun kaupunginmuseo — PDM","URL":"https://finna.fi/Record/tmk.161012261024600","ImageURL":"https://api.finna.fi/Cover/Show?source=Solr&id=tmk.161012261024600&index=0&size=large","ObjectID":91821},{"Title":"Tamperelaisia rakennusmestareita Turun hautausmaalla; ulkokuva; ryhmäkuva","Artist":"","Date":"1955","Medium":"","CreditLine":"Turun kaupunginmuseo — PDM","URL":"https://finna.fi/Record/tmk.161012852018200","ImageURL":"https://api.finna.fi/Cover/Show?source=Solr&id=tmk.161012852018200&index=0&size=large","ObjectID":93189},{"Title":"Liitukalliot; opetustaulu","Artist":"Leipziger Schulbildervarlag von F. E. Wachsmuth","Date":"","Medium":"","CreditLine":"Turun kaupunginmuseo — CC BY 4.0","URL":"https://finna.fi/Record/tmk.161016190206800","ImageURL":"https://api.finna.fi/Cover/Show?source=Solr&id=tmk.161016190206800&index=0&size=large","ObjectID":94557},{"Title":"suklaasydänmuotti","Artist":"","Date":"","Medium":"","CreditLine":"Turun kaupunginmuseo — CC BY 4.0","URL":"https://finna.fi/Record/tmk.161017339841400","ImageURL":"https://api.finna.fi/Cover/Show?source=Solr&id=tmk.161017339841400&index=0&size=large","ObjectID":95925},{"Title":"Vim; pesujauhe; vuosinäyte 1961","Artist":"Turun Saippua Oy","Date":"1961","Medium":"","CreditLine":"Turun kaupunginmuseo — CC BY 4.0","URL":"https://finna.fi/Record/tmk.161018040785100","ImageURL":"https://api.finna.fi/Cover/Show?source=Solr&id=tmk.161018040785100&index=0&size=large","ObjectID":97293},{"Title":"Pepsodent Fluor; hammastahna; vuosinäyte 1972","Artist":"Gibbs","Date":"1972","Medium":"","CreditLine":"Turun kaupunginmuseo — CC BY 4.0","URL":"https://finna.fi/Record/tmk.161018775793400","ImageURL":"https://api.finna.fi/Cover/Show?source=Solr&id=tmk.161018775793400&index=0&size=large","ObjectID":98661},{"Title":"Impulse; Temptation; parfyymideodorantti; vuosinäyte 1985","Artist":"","Date":"1985","Medium":"","CreditLine":"Turun kaupunginmuseo — CC BY 4.0","URL":"https://finna.fi/Record/tmk.161019412096500","ImageURL":"https://api.finna.fi/Cover/Show?source=Solr&id=tmk.161019412096500&index=0&size=large","ObjectID":100029},{"Title":"Kalakauppias ja asiakas Kauppatorilla.","Artist":"Turun Sanomat","Date":"1934","Medium":"","CreditLine":"Turun kaupunginmuseo — PDM","URL":"https://finna.fi/Record/tmk.161020271541100","ImageURL":"https://api.finna.fi/Cover/Show?source=Solr&id=tmk.161020271541100&index=0&size=large","ObjectID":101397},{"Title":"vauvanmyssy","Artist":"Vendi Oy","Date":"2001","Medium":"","CreditLine":"Turun kaupunginmuseo — CC BY 4.0","URL":"https://finna.fi/Record/tmk.161020702287500","ImageURL":"https://api.finna.fi/Cover/Show?source=Solr&id=tmk.161020702287500&index=0&size=large","ObjectID":102765},{"Title":"Pojat pelaavat pesäpalloa Kupittaan kentällä.","Artist":"Turun Sanomat","Date":"1928","Medium":"","CreditLine":"Turun kaupunginmuseo — PDM","URL":"https://finna.fi/Record/tmk.161021138586500","ImageURL":"https://api.finna.fi/Cover/Show?source=Solr&id=tmk.161021138586500&index=0&size=large","ObjectID":104133},{"Title":"Moottoripyöräkilpailut. Ruissalo-ajot.","Artist":"Turun Sanomat","Date":"1930","Medium":"","CreditLine":"Turun kaupunginmuseo — PDM","URL":"https://finna.fi/Record/tmk.161021572949100","ImageURL":"https://api.finna.fi/Cover/Show?source=Solr&id=tmk.161021572949100&index=0&size=large","ObjectID":105501},{"Title":"Barkerin tehtaan tuotteita. Tyynyliinoja nipuissa pöydällä.","Artist":"Turun Sanomat","Date":"","Medium":"","CreditLine":"Turun kaupunginmuseo — PDM","URL":"https://finna.fi/Record/tmk.161022102260600","ImageURL":"https://api.finna.fi/Cover/Show?source=Solr&id=tmk.161022102260600&index=0&size=large","ObjectID":106869},{"Title":"Presidentti Relander Turun rautatieasemalla. Presidentin vieressä kenraalimajuri Åkerman (?)","Artist":"Turun Sanomat","Date":"1925","Medium":"","CreditLine":"Turun kaupunginmuseo — PDM","URL":"https://finna.fi/Record/tmk.161022575302600","ImageURL":"https://api.finna.fi/Cover/Show?source=Solr&id=tmk.161022575302600&index=0&size=large","ObjectID":108237},{"Title":"Rintamerkki; Upseerilentäjäkoulu","Artist":"","Date":"","Medium":"","CreditLine":"Turun kaupunginmuseo — CC BY 4.0","URL":"https://finna.fi/Record/tmk.161023129943500","ImageURL":"https://api.finna.fi/Cover/Show?source=Solr&id=tmk.161023129943500&index=0&size=large","ObjectID":109605},{"Title":"Mies sekä nainen pienen lapsen kanssa puutarhassa.","Artist":"Turun Sanomat","Date":"","Medium":"","CreditLine":"Turun kaupunginmuseo — PDM","URL":"https://finna.fi/Record/tmk.161023592070500","ImageURL":"https://api.finna.fi/Cover/Show?source=Solr&id=tmk.161023592070500&index=0&size=large","ObjectID":110973},{"Title":"ryijy","Artist":"","Date":"1930","Medium":"","CreditLine":"Turun kaupunginmuseo — CC BY 4.0","URL":"https://finna.fi/Record/tmk.161024064869400","ImageURL":"https://api.finna.fi/Cover/Show?source=Solr&id=tmk.161024064869400&index=0&size=large","ObjectID":112341},{"Title":"Norjan kruununprinssi Olavin seuruetta istumassa salissa Turun linnassa.","Artist":"Turun Sanomat","Date":"1936","Medium":"","CreditLine":"Turun kaupunginmuseo — PDM","URL":"https://finna.fi/Record/tmk.161024597271800","ImageURL":"https://api.finna.fi/Cover/Show?source=Solr&id=tmk.161024597271800&index=0&size=large","ObjectID":113709},{"Title":"Gatineau; tuote-esite","Artist":"Gatineau","Date":"","Medium":"","CreditLine":"Turun kaupunginmuseo — CC BY 4.0","URL":"https://finna.fi/Record/tmk.161025164593400","ImageURL":"https://api.finna.fi/Cover/Show?source=Solr&id=tmk.161025164593400&index=0&size=large","ObjectID":115077},{"Title":"Parrakas mies rapatun seinän edessä.","Artist":"Turun Sanomat","Date":"","Medium":"","CreditLine":"Turun kaupunginmuseo — PDM","URL":"https://finna.fi/Record/tmk.161025836286500","ImageURL":"https://api.finna.fi/Cover/Show?source=Solr&id=tmk.161025836286500&index=0&size=large","ObjectID":116445},{"Title":"lippu- ja kunniavartioupseeri; tinasotilas","Artist":"","Date":"","Medium":"","CreditLine":"Turun kaupunginmuseo — CC BY 4.0","URL":"https://finna.fi/Record/tmk.161026501592700","ImageURL":"https://api.finna.fi/Cover/Show?source=Solr&id=tmk.161026501592700&index=0&size=large","ObjectID":117813},{"Title":"käsilaukku, olkalaukku; laukku","Artist":"Vuokko Oy","Date":"","Medium":"","CreditLine":"Turun kaupunginmuseo — CC BY 4.0","URL":"https://finna.fi/Record/tmk.161027149318700","ImageURL":"https://api.finna.fi/Cover/Show?source=Solr&id=tmk.161027149318700&index=0&size=large","ObjectID":119181},{"Title":"Lehtipuun oksa.","Artist":"Turun Sanomat","Date":"","Medium":"","CreditLine":"Turun kaupunginmuseo — PDM","URL":"https://finna.fi/Record/tmk.161027745708900","ImageURL":"https://api.finna.fi/Cover/Show?source=Solr&id=tmk.161027745708900&index=0&size=large","ObjectID":120549},{"Title":"leimasin","Artist":"","Date":"","Medium":"","CreditLine":"Turun kaupunginmuseo — CC BY 4.0","URL":"https://finna.fi/Record/tmk.161030125041100","ImageURL":"https://api.finna.fi/Cover/Show?source=Solr&id=tmk.161030125041100&index=0&size=large","ObjectID":121917},{"Title":"paperienkelit; joulukoriste","Artist":"Angelique Troupp","Date":"","Medium":"","CreditLine":"Turun kaupunginmuseo — CC BY 4.0","URL":"https://finna.fi/Record/tmk.161032193845500","ImageURL":"https://api.finna.fi/Cover/Show?source=Solr&id=tmk.161032193845500&index=0&size=large","ObjectID":123285},{"Title":"Hiomakivi ja alusta","Artist":"Erik   Edvard Leväkari    ent.  Lindén","Date":"","Medium":"","CreditLine":"Turun kaupunginmuseo — CC BY 4.0","URL":"https://finna.fi/Record/tmk.161034269478100","ImageURL":"https://api.finna.fi/Cover/Show?source=Solr&id=tmk.161034269478100&index=0&size=large","ObjectID":124653},{"Title":"Turun maakuntamuseon leimasin","Artist":"","Date":"1981","Medium":"","CreditLine":"Turun kaupunginmuseo — CC BY 4.0","URL":"https://finna.fi/Record/tmk.161040797740900","ImageURL":"https://api.finna.fi/Cover/Show?source=Solr&id=tmk.161040797740900&index=0&size=large","ObjectID":126021},{"Title":"nokkamuki","Artist":"","Date":"","Medium":"","CreditLine":"Turun kaupunginmuseo — CC BY 4.0","URL":"https://finna.fi/Record/tmk.161041934734000","ImageURL":"https://api.finna.fi/Cover/Show?source=Solr&id=tmk.161041934734000&index=0&size=large","ObjectID":127389},{"Title":"nuija; puunuija","Artist":"","Date":"","Medium":"","CreditLine":"Turun kaupunginmuseo — CC BY 4.0","URL":"https://finna.fi/Record/tmk.161042977964200","ImageURL":"https://api.finna.fi/Cover/Show?source=Solr&id=tmk.161042977964200&index=0&size=large","ObjectID":128757},{"Title":"Turun Pyöräkellari","Artist":"","Date":"1930","Medium":"","CreditLine":"Turun kaupunginmuseo — PDM","URL":"https://finna.fi/Record/tmk.161045281523100","ImageURL":"https://api.finna.fi/Cover/Show?source=Solr&id=tmk.161045281523100&index=0&size=large","ObjectID":130125},{"Title":"Sininen risti","Artist":"Armas Lähteenkorva; Vapaussoturien Huoltosäätiö","Date":"1967","Medium":"","CreditLine":"Turun kaupunginmuseo — CC BY 4.0","URL":"https://finna.fi/Record/tmk.161048314341300","ImageURL":"https://api.finna.fi/Cover/Show?source=Solr&id=tmk.161048314341300&index=0&size=large","ObjectID":131493},{"Title":"hopeasepän työkalu; kaliperi; länkiharppi","Artist":"","Date":"","Medium":"","CreditLine":"Turun kaupunginmuseo — CC BY 4.0","URL":"https://finna.fi/Record/tmk.161050192513300","ImageURL":"https://api.finna.fi/Cover/Show?source=Solr&id=tmk.161050192513300&index=0&size=large","ObjectID":132861},{"Title":"Sulgan 99 Emulsiovoide; lääketuubi","Artist":"Lääketehdas Leiras Oy Turku","Date":"1900","Medium":"","CreditLine":"Turun kaupunginmuseo — CC BY 4.0","URL":"https://finna.fi/Record/tmk.161051846438800","ImageURL":"https://api.finna.fi/Cover/Show?source=Solr&id=tmk.161051846438800&index=0&size=large","ObjectID":134229},{"Title":"Läntisellä Pitkällä kadulla oleva rakennus pihan puolelta","Artist":"M. Sjöblom","Date":"1956","Medium":"","CreditLine":"Turun kaupunginmuseo — PDM","URL":"https://finna.fi/Record/tmk.161057782979400","ImageURL":"https://api.finna.fi/Cover/Show?source=Solr&id=tmk.161057782979400&index=0&size=large","ObjectID":135597},{"Title":"Arkku ja backgammon-lautapeli (TMM3458 ja TMM3550).","Artist":"Gustaf Welin","Date":"1937","Medium":"","CreditLine":"Turun kaupunginmuseo — PDM","URL":"https://finna.fi/Record/tmk.161058881512900","ImageURL":"https://api.finna.fi/Cover/Show?source=Solr&id=tmk.161058881512900&index=0&size=large","ObjectID":136965},{"Title":"Turun linna. Kahvilan kalusteita, pöytä ja kaksi tuolia.; sisäkuva","Artist":"Carin Bryggman","Date":"1987","Medium":"","CreditLine":"Turun kaupunginmuseo — PDM","URL":"https://finna.fi/Record/tmk.161062026958300","ImageURL":"https://api.finna.fi/Cover/Show?source=Solr&id=tmk.161062026958300&index=0&size=large","ObjectID":138333},{"Title":"Jalostajan ruoka; tuotekuva","Artist":"Aarne Pietinen Oy","Date":"1948","Medium":"","CreditLine":"Turun kaupunginmuseo — PDM","URL":"https://finna.fi/Record/tmk.161071982320600","ImageURL":"https://api.finna.fi/Cover/Show?source=Solr&id=tmk.161071982320600&index=0&size=large","ObjectID":139701},{"Title":"Metsästysseura Tapio; Rintamerkki","Artist":"","Date":"1907","Medium":"","CreditLine":"Turun kaupunginmuseo — CC BY 4.0","URL":"https://finna.fi/Record/tmk.161470290620400","ImageURL":"https://api.finna.fi/Cover/Show?source=Solr&id=tmk.161470290620400&index=0&size=large","ObjectID":141069},{"Title":"Sörjande man vid minnesurna; Sureva mies","Artist":"Tuntematon; Tuntematon","Date":"1700","Medium":"","CreditLine":"WAM Turun kaupungin taidemuseo — PDM","URL":"https://finna.fi/Record/tmk.161626054491400","ImageURL":"https://api.finna.fi/Cover/Show?source=Solr&id=tmk.161626054491400&index=0&size=large","ObjectID":142437},{"Title":"Royal Caramel Crisp pahvikko; Myymäläpakkaus","Artist":"Leaf Oy","Date":"2000","Medium":"","CreditLine":"Turun kaupunginmuseo — CC BY 4.0","URL":"https://finna.fi/Record/tmk.162643182528400","ImageURL":"https://api.finna.fi/Cover/Show?source=Solr&id=tmk.162643182528400&index=0&size=large","ObjectID":143805},{"Title":"3. luokan Vapaudenristi kansalaisansioista pienoiskunniamerkki","Artist":"","Date":"","Medium":"","CreditLine":"Turun kaupunginmuseo — CC BY 4.0","URL":"https://finna.fi/Record/tmk.163466364656900","ImageURL":"https://api.finna.fi/Cover/Show?source=Solr&id=tmk.163466364656900&index=0&size=large","ObjectID":145173},{"Title":"Uusikaupunki, 350-vuotisjuhla pääjuhla; tapahtumakuva","Artist":"","Date":"1967","Medium":"","CreditLine":"The Uusikaupunki museum — PDM","URL":"https://finna.fi/Record/tmk.164275765830100","ImageURL":"https://api.finna.fi/Cover/Show?source=Solr&id=tmk.164275765830100&index=0&size=large","ObjectID":146541},{"Title":"syvä lautanen","Artist":"Suotniemi","Date":"1841","Medium":"","CreditLine":"Turun kaupunginmuseo — CC BY 4.0","URL":"https://finna.fi/Record/tmk.165244285317800","ImageURL":"https://api.finna.fi/Cover/Show?source=Solr&id=tmk.165244285317800&index=0&size=large","ObjectID":147909},{"Title":"juomalasi; olutlasi","Artist":"","Date":"","Medium":"","CreditLine":"Turun kaupunginmuseo — CC BY 4.0","URL":"https://finna.fi/Record/tmk.166374960849100","ImageURL":"https://api.finna.fi/Cover/Show?source=Solr&id=tmk.166374960849100&index=0&size=large","ObjectID":149277},{"Title":"Föri Liplak; lippalakki","Artist":"KUI Design; Kia Nyqvist","Date":"2007","Medium":"","CreditLine":"Turun kaupunginmuseo — CC BY 4.0","URL":"https://finna.fi/Record/tmk.167153834705700","ImageURL":"https://api.finna.fi/Cover/Show?source=Solr&id=tmk.167153834705700&index=0&size=large","ObjectID":150645},{"Title":"Kortiton ruoka ja miten käytän korttiannokseni","Artist":"Aarne Nissinen; Eva Somersalo","Date":"","Medium":"","CreditLine":"The Uusikaupunki museum — PDM","URL":"https://finna.fi/Record/tmk.168353704116200","ImageURL":"https://api.finna.fi/Cover/Show?source=Solr&id=tmk.168353704116200&index=0&size=large","ObjectID":152013},{"Title":"tulitikkurasia / LINNEA; tulitikkurasia; rasia; aski","Artist":"","Date":"","Medium":"","CreditLine":"Turun kaupunginmuseo — CC BY 4.0","URL":"https://finna.fi/Record/tmk.169104572665900","ImageURL":"https://api.finna.fi/Cover/Show?source=Solr&id=tmk.169104572665900&index=0&size=large","ObjectID":153381},{"Title":"Pastori P. Keltto Alahärmän seurakunnan nuorten illassa.; puolikuva; sisäkuva","Artist":"","Date":"1980","Medium":"","CreditLine":"Nuorisotyön tallentaja Nuoperi — PDM","URL":"https://finna.fi/Record/tmk.169875049556900","ImageURL":"https://api.finna.fi/Cover/Show?source=Solr&id=tmk.169875049556900&index=0&size=large","ObjectID":154749},{"Title":"Kläder för klippdocka; Kläder för pappersdocka","Artist":"","Date":"1950","Medium":"","CreditLine":"Pargas hembygdsmuseum — CC BY 4.0","URL":"https://finna.fi/Record/tmk.170478940052700","ImageURL":"https://api.finna.fi/Cover/Show?source=Solr&id=tmk.170478940052700&index=0&size=large","ObjectID":156117},{"Title":"Sampotalo ja näkymä Yliopistonkadulle; ulkokuva; kaupunkikuva","Artist":"Atelier Alppila; Eemeli Reuna","Date":"1938","Medium":"","CreditLine":"Turun kaupunginmuseo — PDM","URL":"https://finna.fi/Record/tmk.170739351270600","ImageURL":"https://api.finna.fi/Cover/Show?source=Solr&id=tmk.170739351270600&index=0&size=large","ObjectID":157485},{"Title":"Koulun suurjuhlien infotilaisuudessa Pirkko Kallio vuonna 1984; sisäkuva; tilannekuva; henkilökuva","Artist":"","Date":"1984","Medium":"","CreditLine":"Nuorisotyön tallentaja Nuoperi — PDM","URL":"https://finna.fi/Record/tmk.171093924735200","ImageURL":"https://api.finna.fi/Cover/Show?source=Solr&id=tmk.171093924735200&index=0&size=large","ObjectID":158853},{"Title":"Saksalainen Grünöl-WC-puhdistusaine; sisäkuva; esinekuva","Artist":"Atelier Alppila; Eemeli Reuna","Date":"1915","Medium":"","CreditLine":"Turun kaupunginmuseo — PDM","URL":"https://finna.fi/Record/tmk.171749455087700","ImageURL":"https://api.finna.fi/Cover/Show?source=Solr&id=tmk.171749455087700&index=0&size=large","ObjectID":160221},{"Title":"Pastillirasia,  Aku Ankka; Pastillirasia; Rasia","Artist":"Hellas","Date":"1986","Medium":"","CreditLine":"Turun kaupunginmuseo — CC BY 4.0","URL":"https://finna.fi/Record/tmk.172708955553200","ImageURL":"https://api.finna.fi/Cover/Show?source=Solr&id=tmk.172708955553200&index=0&size=large","ObjectID":161589},{"Title":"Tuulikki Pietilä; muotokuva","Artist":"Eemeli Reuna","Date":"1935","Medium":"","CreditLine":"Turun kaupunginmuseo — PDM","URL":"https://finna.fi/Record/tmk.173746129576200","ImageURL":"https://api.finna.fi/Cover/Show?source=Solr&id=tmk.173746129576200&index=0&size=large","ObjectID":162957},{"Title":"visiittikorttikuva, Gustaf Ellmén; henkilökuva","Artist":"","Date":"","Medium":"","CreditLine":"The Uusikaupunki museum — PDM","URL":"https://finna.fi/Record/tmk.174316703447300","ImageURL":"https://api.finna.fi/Cover/Show?source=Solr&id=tmk.174316703447300&index=0&size=large","ObjectID":164325},{"Title":"istuinpehmuste; selkänojapehmuste","Artist":"","Date":"","Medium":"","CreditLine":"Turun kaupunginmuseo — CC BY 4.0","URL":"https://finna.fi/Record/tmk.175283584780400","ImageURL":"https://api.finna.fi/Cover/Show?source=Solr&id=tmk.175283584780400&index=0&size=large","ObjectID":165693},{"Title":"Tarjoilija Jarkko Vanninen ja tuntematon pentterityöntekijä Viking I-ravintolan tiskin takana; dokumentaarinen","Artist":"Jarkko Vanninen; Jarkko Vanninen","Date":"1982","Medium":"","CreditLine":"Forum Marinum — PDM","URL":"https://finna.fi/Record/tmk.176277184881500","ImageURL":"https://api.finna.fi/Cover/Show?source=Solr&id=tmk.176277184881500&index=0&size=large","ObjectID":167061},{"Title":"miesten puku / frakki (housut)","Artist":"L. Eskola","Date":"1920","Medium":"","CreditLine":"Turun kaupunginmuseo — CC BY 4.0","URL":"https://finna.fi/Record/tmk.177665523565500","ImageURL":"https://api.finna.fi/Cover/Show?source=Solr&id=tmk.177665523565500&index=0&size=large","ObjectID":168429}]