[{"Title":"Kansakoulu_ Porthaninkatu 8_6_III_4","Artist":"","Date":"","Medium":"","CreditLine":"Helsinki City Archives — CC BY 4.0","URL":"https://finna.fi/Record/hka.139878174949000_147400872701200","ImageURL":"https://api.finna.fi/Cover/Show?source=Solr&id=hka.139878174949000_147400872701200&index=0&size=large","ObjectID":1284},{"Title":"0010_Hietarannan uimaranta_Järjestysmerkkejä","Artist":"","Date":"","Medium":"","CreditLine":"Helsinki City Archives — CC BY 4.0","URL":"https://finna.fi/Record/hka.139878174949000_150366677991200","ImageURL":"https://api.finna.fi/Cover/Show?source=Solr&id=hka.139878174949000_150366677991200&index=0&size=large","ObjectID":2652},{"Title":"Kulosaaren kirkkoherra Werner Wirénin vaimo Sylvia Wirén ja tyttäret Monica ja Magdalena metsän reunalla, tytöillä marjakorit","Artist":"","Date":"1938","Medium":"","CreditLine":"Helsinki City Museum — PDM","URL":"https://finna.fi/Record/hkm.03A22EF6-EE8A-4078-A903-5BF1AE74B633","ImageURL":"https://api.finna.fi/Cover/Show?source=Solr&id=hkm.03A22EF6-EE8A-4078-A903-5BF1AE74B633&index=0&size=large","ObjectID":4020},{"Title":"Helsingin olympiakisat 1952, Soutustadion, melontakilpailut","Artist":"Kannisto, Väinö Aleksi","Date":"1952","Medium":"","CreditLine":"Helsinki City Museum — PDM","URL":"https://finna.fi/Record/hkm.0D358AB3-1FD2-4D10-AF60-1123EBA1F831","ImageURL":"https://api.finna.fi/Cover/Show?source=Solr&id=hkm.0D358AB3-1FD2-4D10-AF60-1123EBA1F831&index=0&size=large","ObjectID":5388},{"Title":"Kolme pikkupoikaa Sörnäisten rannassa","Artist":"Heinonen, Eino","Date":"1950","Medium":"","CreditLine":"Helsinki City Museum — PDM","URL":"https://finna.fi/Record/hkm.17408938-14FB-4FD8-AEAC-A6D2285F218A","ImageURL":"https://api.finna.fi/Cover/Show?source=Solr&id=hkm.17408938-14FB-4FD8-AEAC-A6D2285F218A&index=0&size=large","ObjectID":6756},{"Title":"Kallion kansakoulun pihalla","Artist":"Rista, Simo","Date":"1970","Medium":"","CreditLine":"Helsinki City Museum — PDM","URL":"https://finna.fi/Record/hkm.20B99DD4-BE09-4FC3-88E5-D93704E32CA6","ImageURL":"https://api.finna.fi/Cover/Show?source=Solr&id=hkm.20B99DD4-BE09-4FC3-88E5-D93704E32CA6&index=0&size=large","ObjectID":8124},{"Title":"Vanha kirkko Antinkatu 6 eli Lönnrotinkatu 6","Artist":"Nyblin, Daniel","Date":"1890","Medium":"","CreditLine":"Helsinki City Museum — PDM","URL":"https://finna.fi/Record/hkm.2A2C2E51-0199-4333-83E9-3A14C2B08C92","ImageURL":"https://api.finna.fi/Cover/Show?source=Solr&id=hkm.2A2C2E51-0199-4333-83E9-3A14C2B08C92&index=0&size=large","ObjectID":9492},{"Title":"Äiti ja tytär parvekkeella","Artist":"Jernvall, Juha","Date":"1960","Medium":"","CreditLine":"Helsinki City Museum — PDM","URL":"https://finna.fi/Record/hkm.3372DD43-26CE-45B3-A4C1-2AA29153FD01","ImageURL":"https://api.finna.fi/Cover/Show?source=Solr&id=hkm.3372DD43-26CE-45B3-A4C1-2AA29153FD01&index=0&size=large","ObjectID":10860},{"Title":"Zacharias Topeliusskolan koulurakennus Topeliuksenkadulta nähtynä","Artist":"Heinonen, Eino","Date":"1950","Medium":"","CreditLine":"Helsinki City Museum — PDM","URL":"https://finna.fi/Record/hkm.3CE7026E-924E-4FBB-BD21-B4C0C9B3354C","ImageURL":"https://api.finna.fi/Cover/Show?source=Solr&id=hkm.3CE7026E-924E-4FBB-BD21-B4C0C9B3354C&index=0&size=large","ObjectID":12228},{"Title":"Nuoret miehet kenkäostoksilla Elannon jalkinemyymälässä, Helsinginkatu 2","Artist":"","Date":"1955","Medium":"","CreditLine":"Helsinki City Museum — PDM","URL":"https://finna.fi/Record/hkm.4673EDA2-008F-462D-A5F9-49C8099F706E","ImageURL":"https://api.finna.fi/Cover/Show?source=Solr&id=hkm.4673EDA2-008F-462D-A5F9-49C8099F706E&index=0&size=large","ObjectID":13596},{"Title":"Helsingin Taidehalli","Artist":"Heinonen, Eino","Date":"1962","Medium":"","CreditLine":"Helsinki City Museum — PDM","URL":"https://finna.fi/Record/hkm.4F992FD4-EC3D-4FE9-86D7-1D1EF87A8451","ImageURL":"https://api.finna.fi/Cover/Show?source=Solr&id=hkm.4F992FD4-EC3D-4FE9-86D7-1D1EF87A8451&index=0&size=large","ObjectID":14964},{"Title":"Aina Lindfors (häädetty)","Artist":"Hakli, Kari","Date":"1971","Medium":"","CreditLine":"Helsinki City Museum — PDM","URL":"https://finna.fi/Record/hkm.58DB297E-105E-46F1-82DD-316860BA6E6E","ImageURL":"https://api.finna.fi/Cover/Show?source=Solr&id=hkm.58DB297E-105E-46F1-82DD-316860BA6E6E&index=0&size=large","ObjectID":16332},{"Title":"Tyttö talon pihalla","Artist":"Kannisto, Väinö Aleksi","Date":"1948","Medium":"","CreditLine":"Helsinki City Museum — PDM","URL":"https://finna.fi/Record/hkm.6239FBE7-EFF0-4A92-A049-1CEA61A10BA7","ImageURL":"https://api.finna.fi/Cover/Show?source=Solr&id=hkm.6239FBE7-EFF0-4A92-A049-1CEA61A10BA7&index=0&size=large","ObjectID":17700},{"Title":"Lauri Eskolan häät, sulhanen ja morsian tanssivat häävalssia","Artist":"Kannisto, Väinö Aleksi","Date":"1952","Medium":"","CreditLine":"Helsinki City Museum — PDM","URL":"https://finna.fi/Record/hkm.6B9EA760-FE1E-4014-89E7-C54FEED2BF1E","ImageURL":"https://api.finna.fi/Cover/Show?source=Solr&id=hkm.6B9EA760-FE1E-4014-89E7-C54FEED2BF1E&index=0&size=large","ObjectID":19068},{"Title":"Oy Shell Ab, Sörnäisten varasto","Artist":"","Date":"1962","Medium":"","CreditLine":"Helsinki City Museum — PDM","URL":"https://finna.fi/Record/hkm.756CB62C-5E6D-4A98-8788-7FFB7886F14E","ImageURL":"https://api.finna.fi/Cover/Show?source=Solr&id=hkm.756CB62C-5E6D-4A98-8788-7FFB7886F14E&index=0&size=large","ObjectID":20436},{"Title":"Potilaita ja sairaanhoitajia Suomen Punaisen Ristin invaliidisairaalassa","Artist":"Kannisto, Väinö Aleksi","Date":"1942","Medium":"","CreditLine":"Helsinki City Museum — PDM","URL":"https://finna.fi/Record/hkm.7ED2D4CF-A7CF-4791-BAC5-4E1ABAF94579","ImageURL":"https://api.finna.fi/Cover/Show?source=Solr&id=hkm.7ED2D4CF-A7CF-4791-BAC5-4E1ABAF94579&index=0&size=large","ObjectID":21804},{"Title":"Kamppi","Artist":"Rista, Eeva","Date":"1970","Medium":"","CreditLine":"Helsinki City Museum — PDM","URL":"https://finna.fi/Record/hkm.886836D2-FA45-4639-9366-808A90671DB0","ImageURL":"https://api.finna.fi/Cover/Show?source=Solr&id=hkm.886836D2-FA45-4639-9366-808A90671DB0&index=0&size=large","ObjectID":23172},{"Title":"Kotikuva, aviopari kotonaan","Artist":"Kannisto, Väinö Aleksi","Date":"1946","Medium":"","CreditLine":"Helsinki City Museum — PDM","URL":"https://finna.fi/Record/hkm.915FB24F-C7FD-4E74-9546-F3DE9D819474","ImageURL":"https://api.finna.fi/Cover/Show?source=Solr&id=hkm.915FB24F-C7FD-4E74-9546-F3DE9D819474&index=0&size=large","ObjectID":24540},{"Title":"Katunäkymä, jalankulkijoita rakennustyömään ylittävällä väliaikaisella jalkakäytävällä","Artist":"","Date":"1958","Medium":"","CreditLine":"Helsinki City Museum — PDM","URL":"https://finna.fi/Record/hkm.9A7486BC-ECB7-45EA-81F6-18EFD1FE0B70","ImageURL":"https://api.finna.fi/Cover/Show?source=Solr&id=hkm.9A7486BC-ECB7-45EA-81F6-18EFD1FE0B70&index=0&size=large","ObjectID":25908},{"Title":"Ortodoksinen Pyhän Kolminaisuuden kirkko, C","Artist":"","Date":"1960","Medium":"","CreditLine":"Helsinki City Museum — PDM","URL":"https://finna.fi/Record/hkm.A3723C6F-F1B8-4509-83DE-D7AC2460DCA5","ImageURL":"https://api.finna.fi/Cover/Show?source=Solr&id=hkm.A3723C6F-F1B8-4509-83DE-D7AC2460DCA5&index=0&size=large","ObjectID":27276},{"Title":"Kiviset portin pylväät, vasemmalla Elannon myymälärakennus Hertankatu 15:ssä sekä oikealla Eevankadun puutaloja Länsi-Pasilassa","Artist":"Rista, Simo","Date":"1974","Medium":"","CreditLine":"Helsinki City Museum — PDM","URL":"https://finna.fi/Record/hkm.AD2533A9-91A1-42C8-8A9A-41A9E979686E","ImageURL":"https://api.finna.fi/Cover/Show?source=Solr&id=hkm.AD2533A9-91A1-42C8-8A9A-41A9E979686E&index=0&size=large","ObjectID":28644},{"Title":"Saunaseuran vastavalmistunut saunatalo Lauttasaaren Vaskiniemessä","Artist":"von Bonin, Volker","Date":"1952","Medium":"","CreditLine":"Helsinki City Museum — PDM","URL":"https://finna.fi/Record/hkm.B756E62F-0144-4345-AF91-FFFB3AEC2E12","ImageURL":"https://api.finna.fi/Cover/Show?source=Solr&id=hkm.B756E62F-0144-4345-AF91-FFFB3AEC2E12&index=0&size=large","ObjectID":30012},{"Title":"Sofiankatu","Artist":"Rönnberg, Anton","Date":"1933","Medium":"","CreditLine":"Helsinki City Museum — PDM","URL":"https://finna.fi/Record/hkm.C12AE666-77DA-4ABC-8F3F-68DF78280BC7","ImageURL":"https://api.finna.fi/Cover/Show?source=Solr&id=hkm.C12AE666-77DA-4ABC-8F3F-68DF78280BC7&index=0&size=large","ObjectID":31380},{"Title":"Talvinen katunäkymä Hakaniemestä","Artist":"Heinonen, Eino","Date":"1950","Medium":"","CreditLine":"Helsinki City Museum — PDM","URL":"https://finna.fi/Record/hkm.CB642202-1F9E-476E-AEDF-D289E469C835","ImageURL":"https://api.finna.fi/Cover/Show?source=Solr&id=hkm.CB642202-1F9E-476E-AEDF-D289E469C835&index=0&size=large","ObjectID":32748},{"Title":"Helsinginkatu 32, 34","Artist":"Möller, B.","Date":"1966","Medium":"","CreditLine":"Helsinki City Museum — PDM","URL":"https://finna.fi/Record/hkm.D596E741-9CFC-4C4C-8E1A-AA2A5C41E766","ImageURL":"https://api.finna.fi/Cover/Show?source=Solr&id=hkm.D596E741-9CFC-4C4C-8E1A-AA2A5C41E766&index=0&size=large","ObjectID":34116},{"Title":"Työväen vappukulkue Siltasaarenkadulla Pitkänsillan pohjoispäässä 1","Artist":"Rista, Simo","Date":"1973","Medium":"","CreditLine":"Helsinki City Museum — PDM","URL":"https://finna.fi/Record/hkm.DFC2339B-30B3-43C4-9D25-DD28FE2129F4","ImageURL":"https://api.finna.fi/Cover/Show?source=Solr&id=hkm.DFC2339B-30B3-43C4-9D25-DD28FE2129F4&index=0&size=large","ObjectID":35484},{"Title":"Paasivuoren puistikko","Artist":"Rista, Eeva","Date":"1970","Medium":"","CreditLine":"Helsinki City Museum — PDM","URL":"https://finna.fi/Record/hkm.E9F75B3B-145B-484E-B7AA-3B74FA1D6027","ImageURL":"https://api.finna.fi/Cover/Show?source=Solr&id=hkm.E9F75B3B-145B-484E-B7AA-3B74FA1D6027&index=0&size=large","ObjectID":36852},{"Title":"Oy Shell Ab:n huoltoasemaa rakennetaan Espoon Westendissä","Artist":"","Date":"1936","Medium":"","CreditLine":"Helsinki City Museum — PDM","URL":"https://finna.fi/Record/hkm.F3978453-23FB-4080-9170-9E03D36EF784","ImageURL":"https://api.finna.fi/Cover/Show?source=Solr&id=hkm.F3978453-23FB-4080-9170-9E03D36EF784&index=0&size=large","ObjectID":38220},{"Title":"Messuhalli (=Töölön kisahalli), Neuvostoliiton teollisuusnäyttely","Artist":"Kannisto, Väinö Aleksi","Date":"1959","Medium":"","CreditLine":"Helsinki City Museum — PDM","URL":"https://finna.fi/Record/hkm.FD792507-CA8F-4CEE-9463-B4E5A87DE22A","ImageURL":"https://api.finna.fi/Cover/Show?source=Solr&id=hkm.FD792507-CA8F-4CEE-9463-B4E5A87DE22A&index=0&size=large","ObjectID":39588},{"Title":"Kivisakasti. Mikkeli, Porrassalmenkatu.","Artist":"Eero Jokilehto","Date":"1963","Medium":"","CreditLine":"Mikkeli City Museums — PDM","URL":"https://finna.fi/Record/mkm.166867575810200","ImageURL":"https://api.finna.fi/Cover/Show?source=Solr&id=mkm.166867575810200&index=0&size=large","ObjectID":40956},{"Title":"Karikon ylikäytävä.","Artist":"Valokuvaamo Väisänen","Date":"1950","Medium":"","CreditLine":"Mikkeli City Museums — PDM","URL":"https://finna.fi/Record/mkm.166867595542600","ImageURL":"https://api.finna.fi/Cover/Show?source=Solr&id=mkm.166867595542600&index=0&size=large","ObjectID":42324},{"Title":"Talvisodan pommituksissa vaurioitunut rakennus Mikkelissä","Artist":"Eino Torniainen","Date":"1940","Medium":"","CreditLine":"Mikkeli City Museums — PDM","URL":"https://finna.fi/Record/mkm.177926074808800","ImageURL":"https://api.finna.fi/Cover/Show?source=Solr&id=mkm.177926074808800&index=0&size=large","ObjectID":43692},{"Title":"näkymä Suolahdelta","Artist":"","Date":"1900","Medium":"","CreditLine":"Finnish Heritage Agency — PDM","URL":"https://finna.fi/Record/museovirasto.65d5d3a3-d3ee-41e8-8f7c-f56e748384fa","ImageURL":"https://api.finna.fi/Cover/Show?source=Solr&id=museovirasto.65d5d3a3-d3ee-41e8-8f7c-f56e748384fa&index=0&size=large","ObjectID":45060},{"Title":"Uudenkaarlepyynkoski pohjoisrannalta","Artist":"","Date":"1912","Medium":"","CreditLine":"Finnish Heritage Agency — PDM","URL":"https://finna.fi/Record/museovirasto.cbf91886-edef-4fe4-b41e-753a809abca0","ImageURL":"https://api.finna.fi/Cover/Show?source=Solr&id=museovirasto.cbf91886-edef-4fe4-b41e-753a809abca0&index=0&size=large","ObjectID":46428},{"Title":"Joulu-kalja -etikettejä","Artist":"Turun Kivipaino Oy - Åbo Stentryckeri Ab","Date":"1962","Medium":"","CreditLine":"Turun kaupunginmuseo — CC BY 4.0","URL":"https://finna.fi/Record/tmk.160988049675400","ImageURL":"https://api.finna.fi/Cover/Show?source=Solr&id=tmk.160988049675400&index=0&size=large","ObjectID":47796},{"Title":"tapettinäyte","Artist":"","Date":"","Medium":"","CreditLine":"Turun kaupunginmuseo — CC BY 4.0","URL":"https://finna.fi/Record/tmk.160988295615400","ImageURL":"https://api.finna.fi/Cover/Show?source=Solr&id=tmk.160988295615400&index=0&size=large","ObjectID":49164},{"Title":"reunanauha; tapettinäyte","Artist":"","Date":"","Medium":"","CreditLine":"Turun kaupunginmuseo — CC BY 4.0","URL":"https://finna.fi/Record/tmk.160988527924200","ImageURL":"https://api.finna.fi/Cover/Show?source=Solr&id=tmk.160988527924200&index=0&size=large","ObjectID":50532},{"Title":"Oka Kahvi Oy -tulitikkuetikettejä","Artist":"Turun Kivipaino Oy - Åbo Stentryckeri Ab","Date":"1951","Medium":"","CreditLine":"Turun kaupunginmuseo — CC BY 4.0","URL":"https://finna.fi/Record/tmk.160988741311700","ImageURL":"https://api.finna.fi/Cover/Show?source=Solr&id=tmk.160988741311700&index=0&size=large","ObjectID":51900},{"Title":"tapettinäyte","Artist":"","Date":"","Medium":"","CreditLine":"Turun kaupunginmuseo — CC BY 4.0","URL":"https://finna.fi/Record/tmk.160989000793300","ImageURL":"https://api.finna.fi/Cover/Show?source=Solr&id=tmk.160989000793300&index=0&size=large","ObjectID":53268},{"Title":"pyyheliinatelineen edusta; pyyheliinapeite","Artist":"","Date":"","Medium":"","CreditLine":"The Uusikaupunki museum — PDM","URL":"https://finna.fi/Record/tmk.160989306900700","ImageURL":"https://api.finna.fi/Cover/Show?source=Solr&id=tmk.160989306900700&index=0&size=large","ObjectID":54636},{"Title":"tapetti; tapettinäyte","Artist":"","Date":"","Medium":"","CreditLine":"Turun kaupunginmuseo — CC BY 4.0","URL":"https://finna.fi/Record/tmk.160989567308500","ImageURL":"https://api.finna.fi/Cover/Show?source=Solr&id=tmk.160989567308500&index=0&size=large","ObjectID":56004},{"Title":"luonnos","Artist":"Turun Kivipaino Oy - Åbo Stentryckeri Ab","Date":"1959","Medium":"","CreditLine":"Turun kaupunginmuseo — CC BY 4.0","URL":"https://finna.fi/Record/tmk.160989815405800","ImageURL":"https://api.finna.fi/Cover/Show?source=Solr&id=tmk.160989815405800&index=0&size=large","ObjectID":57372},{"Title":"naisen käsineet; käsineet","Artist":"","Date":"1950","Medium":"","CreditLine":"The Uusikaupunki museum — PDM","URL":"https://finna.fi/Record/tmk.160990124046400","ImageURL":"https://api.finna.fi/Cover/Show?source=Solr&id=tmk.160990124046400&index=0&size=large","ObjectID":58740},{"Title":"pussi","Artist":"Turun Offsetpaino Oy","Date":"1980","Medium":"","CreditLine":"Turun kaupunginmuseo — CC BY 4.0","URL":"https://finna.fi/Record/tmk.160990343046900","ImageURL":"https://api.finna.fi/Cover/Show?source=Solr&id=tmk.160990343046900&index=0&size=large","ObjectID":60108},{"Title":"kellonavain; taskukellon avain","Artist":"Elias Eliasson Lindstedt","Date":"1800","Medium":"","CreditLine":"Turun kaupunginmuseo — CC BY 4.0","URL":"https://finna.fi/Record/tmk.160990655013400","ImageURL":"https://api.finna.fi/Cover/Show?source=Solr&id=tmk.160990655013400&index=0&size=large","ObjectID":61476},{"Title":"kynttilänjalka","Artist":"","Date":"1860","Medium":"","CreditLine":"The Uusikaupunki museum — PDM","URL":"https://finna.fi/Record/tmk.160991189798400","ImageURL":"https://api.finna.fi/Cover/Show?source=Solr&id=tmk.160991189798400&index=0&size=large","ObjectID":62844},{"Title":"huivi; kirkkosilkki; silkkihuivi","Artist":"","Date":"","Medium":"","CreditLine":"The Uusikaupunki museum — PDM","URL":"https://finna.fi/Record/tmk.160991915322400","ImageURL":"https://api.finna.fi/Cover/Show?source=Solr&id=tmk.160991915322400&index=0&size=large","ObjectID":64212},{"Title":"lasipurkki","Artist":"","Date":"","Medium":"","CreditLine":"Turun kaupunginmuseo — CC BY 4.0","URL":"https://finna.fi/Record/tmk.160992929897000","ImageURL":"https://api.finna.fi/Cover/Show?source=Solr&id=tmk.160992929897000&index=0&size=large","ObjectID":65580},{"Title":"haarukka","Artist":"","Date":"","Medium":"","CreditLine":"Turun kaupunginmuseo — CC BY 4.0","URL":"https://finna.fi/Record/tmk.160994475466700","ImageURL":"https://api.finna.fi/Cover/Show?source=Solr&id=tmk.160994475466700&index=0&size=large","ObjectID":66948},{"Title":"Ida Karolina Gadd; Nimikilpi; hautamuistomerkki","Artist":"Tuntematon; Jorma Kontio","Date":"1923","Medium":"","CreditLine":"Forum Marinum — CC BY 4.0","URL":"https://finna.fi/Record/tmk.160995757563400","ImageURL":"https://api.finna.fi/Cover/Show?source=Solr&id=tmk.160995757563400&index=0&size=large","ObjectID":68316},{"Title":"Kaupunkikuva, katunäkymä, Koulukatu","Artist":"","Date":"1930","Medium":"","CreditLine":"The Uusikaupunki museum — PDM","URL":"https://finna.fi/Record/tmk.160996952338200","ImageURL":"https://api.finna.fi/Cover/Show?source=Solr&id=tmk.160996952338200&index=0&size=large","ObjectID":69684},{"Title":"naisten hattu","Artist":"","Date":"","Medium":"","CreditLine":"Turun kaupunginmuseo — CC BY 4.0","URL":"https://finna.fi/Record/tmk.160997584495700","ImageURL":"https://api.finna.fi/Cover/Show?source=Solr&id=tmk.160997584495700&index=0&size=large","ObjectID":71052},{"Title":"U.S.A.T. Northern Pacific, jolla kalantilainen Toivo Pentti purjehti 1920-luvun alkupuolella.","Artist":"Vilppu Aalto","Date":"","Medium":"","CreditLine":"The Uusikaupunki museum — PDM","URL":"https://finna.fi/Record/tmk.160998112368400","ImageURL":"https://api.finna.fi/Cover/Show?source=Solr&id=tmk.160998112368400&index=0&size=large","ObjectID":72420},{"Title":"visiittikorttikuva, miehen rintakuva, J. W. Nyblom; henkilökuva","Artist":"Aune's Fotografi Atelier","Date":"","Medium":"","CreditLine":"The Uusikaupunki museum — PDM","URL":"https://finna.fi/Record/tmk.160998574930500","ImageURL":"https://api.finna.fi/Cover/Show?source=Solr&id=tmk.160998574930500&index=0&size=large","ObjectID":73788},{"Title":"Uudenkaupungin satama, Hepokari. Höyrylaiva Kastelholm saapuu satamaan.","Artist":"Valokuvaamo Varjus","Date":"1960","Medium":"","CreditLine":"The Uusikaupunki museum — PDM","URL":"https://finna.fi/Record/tmk.160999003268500","ImageURL":"https://api.finna.fi/Cover/Show?source=Solr&id=tmk.160999003268500&index=0&size=large","ObjectID":75156},{"Title":"Höyrylaiva Cantoise","Artist":"","Date":"1902","Medium":"","CreditLine":"The Uusikaupunki museum — PDM","URL":"https://finna.fi/Record/tmk.160999473383600","ImageURL":"https://api.finna.fi/Cover/Show?source=Solr&id=tmk.160999473383600&index=0&size=large","ObjectID":76524},{"Title":"nainen lumisella pihalla Uudessakaupungissa, potkukelkka; henkilökuva; ulkokuva","Artist":"","Date":"1954","Medium":"","CreditLine":"The Uusikaupunki museum — PDM","URL":"https://finna.fi/Record/tmk.160999820520900","ImageURL":"https://api.finna.fi/Cover/Show?source=Solr&id=tmk.160999820520900&index=0&size=large","ObjectID":77892},{"Title":"Kehyslistamallilaatta","Artist":"","Date":"","Medium":"","CreditLine":"Turun kaupunginmuseo — CC BY 4.0","URL":"https://finna.fi/Record/tmk.161000815517200","ImageURL":"https://api.finna.fi/Cover/Show?source=Solr&id=tmk.161000815517200&index=0&size=large","ObjectID":79260},{"Title":"leninki","Artist":"Modelia Oy","Date":"1970","Medium":"","CreditLine":"Turun kaupunginmuseo — CC BY 4.0","URL":"https://finna.fi/Record/tmk.161002317995600","ImageURL":"https://api.finna.fi/Cover/Show?source=Solr&id=tmk.161002317995600&index=0&size=large","ObjectID":80628},{"Title":"naisten kengät; sandaalit, hippikengät","Artist":"","Date":"1979","Medium":"","CreditLine":"Turun kaupunginmuseo — CC BY 4.0","URL":"https://finna.fi/Record/tmk.161003903880700","ImageURL":"https://api.finna.fi/Cover/Show?source=Solr&id=tmk.161003903880700&index=0&size=large","ObjectID":81996},{"Title":"Laivamuotokuva \"Carradale\"","Artist":"","Date":"","Medium":"","CreditLine":"Forum Marinum — PDM","URL":"https://finna.fi/Record/tmk.161005492975500","ImageURL":"https://api.finna.fi/Cover/Show?source=Solr&id=tmk.161005492975500&index=0&size=large","ObjectID":83364},{"Title":"vati","Artist":"Villeroy & Boch","Date":"","Medium":"","CreditLine":"Turun kaupunginmuseo — CC BY 4.0","URL":"https://finna.fi/Record/tmk.161006700295700","ImageURL":"https://api.finna.fi/Cover/Show?source=Solr&id=tmk.161006700295700&index=0&size=large","ObjectID":84732},{"Title":"Marttanuken kansallispuvun esiliina","Artist":"Turun Martta-Nukketeollisuus","Date":"1950","Medium":"","CreditLine":"Turun kaupunginmuseo — CC BY 4.0","URL":"https://finna.fi/Record/tmk.161007663934500","ImageURL":"https://api.finna.fi/Cover/Show?source=Solr&id=tmk.161007663934500&index=0&size=large","ObjectID":86100},{"Title":"matto; räsymatto","Artist":"Hilja Lehtinen","Date":"1940","Medium":"","CreditLine":"Turun kaupunginmuseo — CC BY 4.0","URL":"https://finna.fi/Record/tmk.161008712108100","ImageURL":"https://api.finna.fi/Cover/Show?source=Solr&id=tmk.161008712108100&index=0&size=large","ObjectID":87468},{"Title":"Indreniuksen albumi 1","Artist":"","Date":"1879","Medium":"","CreditLine":"Forum Marinum — PDM","URL":"https://finna.fi/Record/tmk.161009966961700","ImageURL":"https://api.finna.fi/Cover/Show?source=Solr&id=tmk.161009966961700&index=0&size=large","ObjectID":88836},{"Title":"lautanen","Artist":"","Date":"1736","Medium":"","CreditLine":"Turun kaupunginmuseo — CC BY 4.0","URL":"https://finna.fi/Record/tmk.161011649072300","ImageURL":"https://api.finna.fi/Cover/Show?source=Solr&id=tmk.161011649072300&index=0&size=large","ObjectID":90204},{"Title":"Kuitian kartano.","Artist":"Turun Sanomat","Date":"","Medium":"","CreditLine":"Turun kaupunginmuseo — PDM","URL":"https://finna.fi/Record/tmk.161012184094100","ImageURL":"https://api.finna.fi/Cover/Show?source=Solr&id=tmk.161012184094100&index=0&size=large","ObjectID":91572},{"Title":"Vasaramäen koulun liikuntasali; sisäkuva","Artist":"","Date":"1952","Medium":"","CreditLine":"Turun kaupunginmuseo — PDM","URL":"https://finna.fi/Record/tmk.161012647848600","ImageURL":"https://api.finna.fi/Cover/Show?source=Solr&id=tmk.161012647848600&index=0&size=large","ObjectID":92940},{"Title":"maljakko","Artist":"Valentina Modig-Manuel","Date":"1959","Medium":"","CreditLine":"Turun kaupunginmuseo — CC BY 4.0","URL":"https://finna.fi/Record/tmk.161016023030100","ImageURL":"https://api.finna.fi/Cover/Show?source=Solr&id=tmk.161016023030100&index=0&size=large","ObjectID":94308},{"Title":"Vaateliike Ki-Ma, Turku.; sisäkuva","Artist":"Foto Rautavuori; Carin Bryggman","Date":"1956","Medium":"","CreditLine":"Turun kaupunginmuseo — PDM","URL":"https://finna.fi/Record/tmk.161017209720700","ImageURL":"https://api.finna.fi/Cover/Show?source=Solr&id=tmk.161017209720700&index=0&size=large","ObjectID":95676},{"Title":"Liiketyöntekijöiden kesäkoti Hiiriluodon päärakennus Ruissalossa; yleiskuva","Artist":"Rusko Reuna","Date":"1958","Medium":"","CreditLine":"Turun kaupunginmuseo — PDM","URL":"https://finna.fi/Record/tmk.161017926294000","ImageURL":"https://api.finna.fi/Cover/Show?source=Solr&id=tmk.161017926294000&index=0&size=large","ObjectID":97044},{"Title":"Pepsodent Fluor; hammastahna; vuosinäyte 1970","Artist":"Gibbs","Date":"1970","Medium":"","CreditLine":"Turun kaupunginmuseo — CC BY 4.0","URL":"https://finna.fi/Record/tmk.161018615442900","ImageURL":"https://api.finna.fi/Cover/Show?source=Solr&id=tmk.161018615442900&index=0&size=large","ObjectID":98412},{"Title":"Bore II -laiva","Artist":"","Date":"","Medium":"","CreditLine":"Turun kaupunginmuseo — PDM","URL":"https://finna.fi/Record/tmk.161019301980800","ImageURL":"https://api.finna.fi/Cover/Show?source=Solr&id=tmk.161019301980800&index=0&size=large","ObjectID":99780},{"Title":"Tetra Rex; Valio ykkösmaito; maitotölkin aihio","Artist":"Tetra Pak","Date":"2003","Medium":"","CreditLine":"Turun kaupunginmuseo — CC BY 4.0","URL":"https://finna.fi/Record/tmk.161020169488100","ImageURL":"https://api.finna.fi/Cover/Show?source=Solr&id=tmk.161020169488100&index=0&size=large","ObjectID":101148},{"Title":"kaadin; kermakko","Artist":"Kupittaan Savi Oy","Date":"1960","Medium":"","CreditLine":"Turun kaupunginmuseo — CC BY 4.0","URL":"https://finna.fi/Record/tmk.161020634340900","ImageURL":"https://api.finna.fi/Cover/Show?source=Solr&id=tmk.161020634340900&index=0&size=large","ObjectID":102516},{"Title":"Turun messut. P.C.Rettig & Co:n tupakkatehtaan näyttelyosasto Tyttölyseon tiloissa.","Artist":"Turun Sanomat","Date":"1929","Medium":"","CreditLine":"Turun kaupunginmuseo — PDM","URL":"https://finna.fi/Record/tmk.161021049550300","ImageURL":"https://api.finna.fi/Cover/Show?source=Solr&id=tmk.161021049550300&index=0&size=large","ObjectID":103884},{"Title":"Jäinen laiva Carelia Turun satamassa.","Artist":"Turun Sanomat","Date":"1925","Medium":"","CreditLine":"Turun kaupunginmuseo — PDM","URL":"https://finna.fi/Record/tmk.161021499819500","ImageURL":"https://api.finna.fi/Cover/Show?source=Solr&id=tmk.161021499819500&index=0&size=large","ObjectID":105252},{"Title":"Miesten polkupyörä.","Artist":"Turun Sanomat","Date":"","Medium":"","CreditLine":"Turun kaupunginmuseo — PDM","URL":"https://finna.fi/Record/tmk.161022002359400","ImageURL":"https://api.finna.fi/Cover/Show?source=Solr&id=tmk.161022002359400&index=0&size=large","ObjectID":106620},{"Title":"lääketölkki","Artist":"Rörstrand  Porslinsfabrik","Date":"","Medium":"","CreditLine":"Turun kaupunginmuseo — CC BY 4.0","URL":"https://finna.fi/Record/tmk.161022485668500","ImageURL":"https://api.finna.fi/Cover/Show?source=Solr&id=tmk.161022485668500&index=0&size=large","ObjectID":107988},{"Title":"Lapsia Turun uimaseuran uimakoulussa.","Artist":"Turun Sanomat","Date":"1934","Medium":"","CreditLine":"Turun kaupunginmuseo — PDM","URL":"https://finna.fi/Record/tmk.161023030609100","ImageURL":"https://api.finna.fi/Cover/Show?source=Solr&id=tmk.161023030609100&index=0&size=large","ObjectID":109356},{"Title":"Aurtua (Eerik Pommerilainen); Kolikko","Artist":"","Date":"1405","Medium":"","CreditLine":"Turun kaupunginmuseo — CC BY 4.0","URL":"https://finna.fi/Record/tmk.161023505356500","ImageURL":"https://api.finna.fi/Cover/Show?source=Solr&id=tmk.161023505356500&index=0&size=large","ObjectID":110724},{"Title":"Kaksi lasta istumassa tuoleilla. Lasten takana lamppu ja tauluja.","Artist":"Turun Sanomat","Date":"1916","Medium":"","CreditLine":"Turun kaupunginmuseo — PDM","URL":"https://finna.fi/Record/tmk.161023971798500","ImageURL":"https://api.finna.fi/Cover/Show?source=Solr&id=tmk.161023971798500&index=0&size=large","ObjectID":112092},{"Title":"Turun yliopiston vihkiäisjuhla Turun linnan pihalla. Mieskuoro esittää Nuijamiesten marssin.","Artist":"Turun Sanomat","Date":"1927","Medium":"","CreditLine":"Turun kaupunginmuseo — PDM","URL":"https://finna.fi/Record/tmk.161024510273500","ImageURL":"https://api.finna.fi/Cover/Show?source=Solr&id=tmk.161024510273500&index=0&size=large","ObjectID":113460},{"Title":"Ihmiset laulavat avoimen haudan äärellä.","Artist":"Turun Sanomat","Date":"1920","Medium":"","CreditLine":"Turun kaupunginmuseo — PDM","URL":"https://finna.fi/Record/tmk.161025077026500","ImageURL":"https://api.finna.fi/Cover/Show?source=Solr&id=tmk.161025077026500&index=0&size=large","ObjectID":114828},{"Title":"kynttilänjalka","Artist":"Johan Lindblad","Date":"","Medium":"","CreditLine":"Turun kaupunginmuseo — CC BY 4.0","URL":"https://finna.fi/Record/tmk.161025674784800","ImageURL":"https://api.finna.fi/Cover/Show?source=Solr&id=tmk.161025674784800&index=0&size=large","ObjectID":116196},{"Title":"Puutarhaa hoitamassa huvilan omistaja rouva Sofia Vuorela sekä rouva Eva Järvinen ja Jukka-poika.","Artist":"Turun Sanomat","Date":"1943","Medium":"","CreditLine":"Turun kaupunginmuseo — PDM","URL":"https://finna.fi/Record/tmk.161026374347700","ImageURL":"https://api.finna.fi/Cover/Show?source=Solr&id=tmk.161026374347700&index=0&size=large","ObjectID":117564},{"Title":"Lapsia äitiensä sylissä lääkärissä rokotettavina (?)","Artist":"Turun Sanomat","Date":"1947","Medium":"","CreditLine":"Turun kaupunginmuseo — PDM","URL":"https://finna.fi/Record/tmk.161027036570800","ImageURL":"https://api.finna.fi/Cover/Show?source=Solr&id=tmk.161027036570800&index=0&size=large","ObjectID":118932},{"Title":"Porkkanan kylvöä kasvimaalle Kupittaan siirtolapuutarhapalstalla.","Artist":"Turun Sanomat","Date":"1941","Medium":"","CreditLine":"Turun kaupunginmuseo — PDM","URL":"https://finna.fi/Record/tmk.161027611835200","ImageURL":"https://api.finna.fi/Cover/Show?source=Solr&id=tmk.161027611835200&index=0&size=large","ObjectID":120300},{"Title":"kivitaulu","Artist":"","Date":"","Medium":"","CreditLine":"Turun kaupunginmuseo — CC BY 4.0","URL":"https://finna.fi/Record/tmk.161029856394900","ImageURL":"https://api.finna.fi/Cover/Show?source=Solr&id=tmk.161029856394900&index=0&size=large","ObjectID":121668},{"Title":"10 äyriä (Kustaa V); kolikko","Artist":"","Date":"1950","Medium":"","CreditLine":"Turun kaupunginmuseo — CC BY 4.0","URL":"https://finna.fi/Record/tmk.161031755870600","ImageURL":"https://api.finna.fi/Cover/Show?source=Solr&id=tmk.161031755870600&index=0&size=large","ObjectID":123036},{"Title":"Turun historiallisen museon toimiston kyltti","Artist":"","Date":"","Medium":"","CreditLine":"Turun kaupunginmuseo — CC BY 4.0","URL":"https://finna.fi/Record/tmk.161033850008700","ImageURL":"https://api.finna.fi/Cover/Show?source=Solr&id=tmk.161033850008700&index=0&size=large","ObjectID":124404},{"Title":"lasimaalaus","Artist":"Willy Baer","Date":"1912","Medium":"","CreditLine":"Turun kaupunginmuseo — CC BY 4.0","URL":"https://finna.fi/Record/tmk.161040483335000","ImageURL":"https://api.finna.fi/Cover/Show?source=Solr&id=tmk.161040483335000&index=0&size=large","ObjectID":125772},{"Title":"Neilikkaöljy; apteekkipullo; lääkepullo","Artist":"","Date":"1900","Medium":"","CreditLine":"Turun kaupunginmuseo — CC BY 4.0","URL":"https://finna.fi/Record/tmk.161041758114900","ImageURL":"https://api.finna.fi/Cover/Show?source=Solr&id=tmk.161041758114900&index=0&size=large","ObjectID":127140},{"Title":"potta","Artist":"","Date":"","Medium":"","CreditLine":"Turun kaupunginmuseo — CC BY 4.0","URL":"https://finna.fi/Record/tmk.161042860087400","ImageURL":"https://api.finna.fi/Cover/Show?source=Solr&id=tmk.161042860087400&index=0&size=large","ObjectID":128508},{"Title":"Gummi Arabicum; apteekkipurkki","Artist":"Pharmakonin farmaseuttinen tutkimuslaboratorio","Date":"1912","Medium":"","CreditLine":"Turun kaupunginmuseo — CC BY 4.0","URL":"https://finna.fi/Record/tmk.161043938702700","ImageURL":"https://api.finna.fi/Cover/Show?source=Solr&id=tmk.161043938702700&index=0&size=large","ObjectID":129876},{"Title":"Sideharsoa","Artist":"","Date":"1905","Medium":"","CreditLine":"Turun kaupunginmuseo — CC BY 4.0","URL":"https://finna.fi/Record/tmk.161047839065300","ImageURL":"https://api.finna.fi/Cover/Show?source=Solr&id=tmk.161047839065300&index=0&size=large","ObjectID":131244},{"Title":"Linja-auto Kauppatori - Itäinen Pitkäkatu; Itäisenkadun autoasema","Artist":"H. Attila","Date":"1929","Medium":"","CreditLine":"Turun kaupunginmuseo — PDM","URL":"https://finna.fi/Record/tmk.161049729756600","ImageURL":"https://api.finna.fi/Cover/Show?source=Solr&id=tmk.161049729756600&index=0&size=large","ObjectID":132612},{"Title":"Diabaryl; lasipurkki; lääkepurkki","Artist":"Oy Medica ab","Date":"1960","Medium":"","CreditLine":"Turun kaupunginmuseo — CC BY 4.0","URL":"https://finna.fi/Record/tmk.161051679966500","ImageURL":"https://api.finna.fi/Cover/Show?source=Solr&id=tmk.161051679966500&index=0&size=large","ObjectID":133980},{"Title":"rintamerkki","Artist":"","Date":"1900","Medium":"","CreditLine":"Turun kaupunginmuseo — CC BY 4.0","URL":"https://finna.fi/Record/tmk.161053577580300","ImageURL":"https://api.finna.fi/Cover/Show?source=Solr&id=tmk.161053577580300&index=0&size=large","ObjectID":135348},{"Title":"Miehen muotokuva; muotokuva","Artist":"Johannes Schalin","Date":"1900","Medium":"","CreditLine":"Turun kaupunginmuseo — PDM","URL":"https://finna.fi/Record/tmk.161058743572500","ImageURL":"https://api.finna.fi/Cover/Show?source=Solr&id=tmk.161058743572500&index=0&size=large","ObjectID":136716},{"Title":"Sampo-yhtiöt, pääkonttori.; sisäkuva","Artist":"Vesa Kinnunen; Carin Bryggman","Date":"1978","Medium":"","CreditLine":"Turun kaupunginmuseo — PDM","URL":"https://finna.fi/Record/tmk.161061359989500","ImageURL":"https://api.finna.fi/Cover/Show?source=Solr&id=tmk.161061359989500&index=0&size=large","ObjectID":138084},{"Title":"Talvimaisema; ulkokuva","Artist":"Johannes Schalin","Date":"1900","Medium":"","CreditLine":"Turun kaupunginmuseo — PDM","URL":"https://finna.fi/Record/tmk.161071227179900","ImageURL":"https://api.finna.fi/Cover/Show?source=Solr&id=tmk.161071227179900&index=0&size=large","ObjectID":139452},{"Title":"Kirkkokahvi; kahvipurkki; metallipurkki","Artist":"Maamiesten kauppa Osakeyhtiön kahvipaahtimo","Date":"","Medium":"","CreditLine":"Turun kaupunginmuseo — CC BY 4.0","URL":"https://finna.fi/Record/tmk.161304115787800","ImageURL":"https://api.finna.fi/Cover/Show?source=Solr&id=tmk.161304115787800&index=0&size=large","ObjectID":140820},{"Title":"The Marriage Ceremony of the Prince and Princess of Wales; Prinden av Wales m. prinsessa vid bröllopet 1795","Artist":"Tuntematon; Tuntematon; Lontoo John Fairburn","Date":"1795","Medium":"","CreditLine":"WAM Turun kaupungin taidemuseo — PDM","URL":"https://finna.fi/Record/tmk.161625811374800","ImageURL":"https://api.finna.fi/Cover/Show?source=Solr&id=tmk.161625811374800&index=0&size=large","ObjectID":142188},{"Title":"Hepokarin sataman rakennustyömaa, Uusikaupunki; ulkokuva","Artist":"","Date":"1960","Medium":"","CreditLine":"The Uusikaupunki museum — PDM","URL":"https://finna.fi/Record/tmk.162564919431900","ImageURL":"https://api.finna.fi/Cover/Show?source=Solr&id=tmk.162564919431900&index=0&size=large","ObjectID":143556},{"Title":"Santtionrannan leirintäalueen huoltorakennus; ulkokuva","Artist":"Valokuvaamo Varjus","Date":"1967","Medium":"","CreditLine":"The Uusikaupunki museum — PDM","URL":"https://finna.fi/Record/tmk.163221488040800","ImageURL":"https://api.finna.fi/Cover/Show?source=Solr&id=tmk.163221488040800&index=0&size=large","ObjectID":144924},{"Title":"Optisen lennättimen muistomerkki; tapahtumakuva","Artist":"Valokuvaamo Varjus","Date":"1961","Medium":"","CreditLine":"The Uusikaupunki museum — PDM","URL":"https://finna.fi/Record/tmk.164216602539300","ImageURL":"https://api.finna.fi/Cover/Show?source=Solr&id=tmk.164216602539300&index=0&size=large","ObjectID":146292},{"Title":"Helene Reinberg työtovereineen ravintolassa; tilannekuva; sisäkuva","Artist":"J. Reinberg","Date":"1914","Medium":"","CreditLine":"Turun kaupunginmuseo — PDM","URL":"https://finna.fi/Record/tmk.164846751709400","ImageURL":"https://api.finna.fi/Cover/Show?source=Solr&id=tmk.164846751709400&index=0&size=large","ObjectID":147660},{"Title":"esinekuvausta; ulkokuva","Artist":"Frans Malkus Karrakoski","Date":"1920","Medium":"","CreditLine":"The Uusikaupunki museum — PDM","URL":"https://finna.fi/Record/tmk.166315210923400","ImageURL":"https://api.finna.fi/Cover/Show?source=Solr&id=tmk.166315210923400&index=0&size=large","ObjectID":149028},{"Title":"M/S Khatangales laiva Uudenkaupungin telakalla","Artist":"Valokuvaamo Iris","Date":"1965","Medium":"","CreditLine":"The Uusikaupunki museum — PDM","URL":"https://finna.fi/Record/tmk.167050162031400","ImageURL":"https://api.finna.fi/Cover/Show?source=Solr&id=tmk.167050162031400&index=0&size=large","ObjectID":150396},{"Title":"lettyjä ja hakasia; paperipussi; pussi; pakkaus","Artist":"O. Y. Vilénin Tehtaat","Date":"","Medium":"","CreditLine":"Turun kaupunginmuseo — CC BY 4.0","URL":"https://finna.fi/Record/tmk.168059240859400","ImageURL":"https://api.finna.fi/Cover/Show?source=Solr&id=tmk.168059240859400&index=0&size=large","ObjectID":151764},{"Title":"Turun Yliopiston Ylioppilaskunta, Aurasoudut; tapahtumakuva; ulkokuva","Artist":"Atelier Alppila; Atelier Alppila; Eemeli Reuna","Date":"1930","Medium":"","CreditLine":"Turun kaupunginmuseo — PDM","URL":"https://finna.fi/Record/tmk.168924704845300","ImageURL":"https://api.finna.fi/Cover/Show?source=Solr&id=tmk.168924704845300&index=0&size=large","ObjectID":153132},{"Title":"järjestysmies-nauha; käsivarsinauha","Artist":"","Date":"","Medium":"","CreditLine":"Turun kaupunginmuseo — CC BY 4.0","URL":"https://finna.fi/Record/tmk.169700783671000","ImageURL":"https://api.finna.fi/Cover/Show?source=Solr&id=tmk.169700783671000&index=0&size=large","ObjectID":154500},{"Title":"Nuorison taidetapahtuma 1992: Paimion lukion ”Cosi fan tutte” -esitys; dokumentaarinen; tapahtumakuva; tilannekuva; henkilökuva","Artist":"Jari Hakala","Date":"1992","Medium":"","CreditLine":"Nuorisotyön tallentaja Nuoperi — PDM","URL":"https://finna.fi/Record/tmk.170419705454800","ImageURL":"https://api.finna.fi/Cover/Show?source=Solr&id=tmk.170419705454800&index=0&size=large","ObjectID":155868},{"Title":"Pianon soittaja; sisäkuva; lähikuva","Artist":"","Date":"1959","Medium":"","CreditLine":"Nuorisotyön tallentaja Nuoperi — PDM","URL":"https://finna.fi/Record/tmk.170712603670300","ImageURL":"https://api.finna.fi/Cover/Show?source=Solr&id=tmk.170712603670300&index=0&size=large","ObjectID":157236},{"Title":"lottapuvun mitella","Artist":"","Date":"","Medium":"","CreditLine":"Turun kaupunginmuseo — CC BY 4.0","URL":"https://finna.fi/Record/tmk.171018194906900","ImageURL":"https://api.finna.fi/Cover/Show?source=Solr&id=tmk.171018194906900&index=0&size=large","ObjectID":158604},{"Title":"Kesätapahtumassa; dokumentaarinen; tapahtumakuva; tilannekuva; henkilökuva; ulkokuva","Artist":"","Date":"","Medium":"","CreditLine":"Nuorisotyön tallentaja Nuoperi — PDM","URL":"https://finna.fi/Record/tmk.171593640675800","ImageURL":"https://api.finna.fi/Cover/Show?source=Solr&id=tmk.171593640675800&index=0&size=large","ObjectID":159972},{"Title":"Purukumikotelo, Jenkki, Pelastuspartio Bernard ja Bianca; Purukumikotelo; Kotelo","Artist":"Suklaatehdas Hellas Oy","Date":"1978","Medium":"","CreditLine":"Turun kaupunginmuseo — CC BY 4.0","URL":"https://finna.fi/Record/tmk.172560675482100","ImageURL":"https://api.finna.fi/Cover/Show?source=Solr&id=tmk.172560675482100&index=0&size=large","ObjectID":161340},{"Title":"Morogoron nuorisotalo Tansaniassa 1995; dokumentaarinen; henkilökuva; tilannekuva; sisäkuva; tapahtumakuva; tanssikuva","Artist":"","Date":"1995","Medium":"","CreditLine":"Nuorisotyön tallentaja Nuoperi — PDM","URL":"https://finna.fi/Record/tmk.173330374306100","ImageURL":"https://api.finna.fi/Cover/Show?source=Solr&id=tmk.173330374306100&index=0&size=large","ObjectID":162708},{"Title":"koululaiva hinauksessa","Artist":"","Date":"1934","Medium":"","CreditLine":"Forum Marinum — PDM","URL":"https://finna.fi/Record/tmk.174236725029300","ImageURL":"https://api.finna.fi/Cover/Show?source=Solr&id=tmk.174236725029300&index=0&size=large","ObjectID":164076},{"Title":"sitrusviipalepuristin; sitruslohkonpuristin; sitruspuristin","Artist":"","Date":"","Medium":"","CreditLine":"Turun kaupunginmuseo — CC BY 4.0","URL":"https://finna.fi/Record/tmk.175084612261800","ImageURL":"https://api.finna.fi/Cover/Show?source=Solr&id=tmk.175084612261800&index=0&size=large","ObjectID":165444},{"Title":"Uudenkaupungin Villatavaratehdas Oy:n huovat, mainoskuva; mainoskuva","Artist":"Valokuvaamo Varjus","Date":"1975","Medium":"","CreditLine":"The Uusikaupunki museum — PDM","URL":"https://finna.fi/Record/tmk.176164145624700","ImageURL":"https://api.finna.fi/Cover/Show?source=Solr&id=tmk.176164145624700&index=0&size=large","ObjectID":166812},{"Title":"kreppipaperipakkaus; kreppipaperi; pakkaus; paperi","Artist":"Dennison Manufacturing Co.","Date":"","Medium":"","CreditLine":"Turun kaupunginmuseo — CC BY 4.0","URL":"https://finna.fi/Record/tmk.177313085881300","ImageURL":"https://api.finna.fi/Cover/Show?source=Solr&id=tmk.177313085881300&index=0&size=large","ObjectID":168180}]